Day14_parity_checker/parity_checker.v
module parity_checker (
	input a_in ,
	input b_in ,
	input p_in ,
	output error_out
);

assign error_out = a_in ^ b_in ^ p_in ;

endmodule

Day14_parity_checker/tb_parity_checker.v
module tb_parity_checker ;

reg tb_a_in,tb_b_in,tb_p_in ;
wire tb_error_out ;

parity_checker dut (
	.a_in(tb_a_in),.b_in(tb_b_in),.p_in(tb_p_in),.error_out(tb_error_out)
);

initial begin

	tb_a_in = 1'b0 ; tb_b_in = 1'b0 ; tb_p_in = 1'b0 ;
#10	tb_a_in = 1'b0 ; tb_b_in = 1'b0 ; tb_p_in = 1'b1 ;
#10	tb_a_in = 1'b0 ; tb_b_in = 1'b1 ; tb_p_in = 1'b0 ;
#10	tb_a_in = 1'b0 ; tb_b_in = 1'b1 ; tb_p_in = 1'b1 ;
#10	tb_a_in = 1'b1 ; tb_b_in = 1'b0 ; tb_p_in = 1'b0 ;
#10	tb_a_in = 1'b1 ; tb_b_in = 1'b0 ; tb_p_in = 1'b1 ;
#10	tb_a_in = 1'b1 ; tb_b_in = 1'b1 ; tb_p_in = 1'b0 ;
#10	tb_a_in = 1'b1 ; tb_b_in = 1'b1 ; tb_p_in = 1'b1 ;
#10 $finish ;

end

initial begin 

	$dumpfile("tb_parity_checker.vcd");
	$dumpvars(0,tb_parity_checker);
end

endmodule

Day14_parity_checker/tb_parity_checker.vcd
$date
	Wed Nov  5 09:15:00 2025
$end
$version
	Icarus Verilog
$end
$timescale
	1s
$end
$scope module tb_parity_checker $end
$var wire 1 ! tb_error_out $end
$var reg 1 " tb_a_in $end
$var reg 1 # tb_b_in $end
$var reg 1 $ tb_p_in $end
$scope module dut $end
$var wire 1 " a_in $end
$var wire 1 # b_in $end
$var wire 1 ! error_out $end
$var wire 1 $ p_in $end
$upscope $end
$upscope $end
$enddefinitions $end
#0
$dumpvars
0$
0#
0"
0!
$end
#10
1!
1$
#20
0$
1#
#30
0!
1$
#40
1!
0$
0#
1"
#50
0!
1$
#60
0$
1#
#70
1!
1$
