Day23_parity_generator/parity_generator.v
module parity_generator (
	input [7:0]data_in ,
	output reg even_parity ,
	output reg odd_parity 
);
integer i ;
always @(*) begin
	even_parity = 0 ;
	for(i=0 ; i<8 ; i = i+1 ) begin

		even_parity = even_parity ^ data_in[i] ;
	end
	odd_parity = ~even_parity ;
end

endmodule

Day23_parity_generator/tb_parity_generator.v
module tb_parity_generator;

    reg  [7:0] tb_data_in;
    wire tb_even_parity;
    wire tb_odd_parity;

    parity_generator dut (
        .data_in(tb_data_in),
        .even_parity(tb_even_parity),
        .odd_parity(tb_odd_parity)
    );

    integer k;

    initial begin
        for (k = 0; k < 255; k = k + 1) begin
            tb_data_in = k;
	    #1;
        end
	$finish;
end

	initial begin
		      $dumpfile("tb_parity_generator.vcd");
                      $dumpvars(0, tb_parity_generator);

	end
endmodule

Day23_parity_generator/tb_parity_generator.vcd
$date
	Wed Nov 12 07:57:04 2025
$end
$version
	Icarus Verilog
$end
$timescale
	1s
$end
$scope module tb_parity_generator $end
$var wire 1 ! tb_odd_parity $end
$var wire 1 " tb_even_parity $end
$var reg 8 # tb_data_in [7:0] $end
$var integer 32 $ k [31:0] $end
$scope module dut $end
$var wire 8 % data_in [7:0] $end
$var reg 1 " even_parity $end
$var reg 1 ! odd_parity $end
$var integer 32 & i [31:0] $end
$upscope $end
$upscope $end
$enddefinitions $end
#0
$dumpvars
b1000 &
b0 %
b0 $
b0 #
0"
1!
$end
#1
0!
1"
b1000 &
b1 #
b1 %
b1 $
#2
b1000 &
1"
b10 #
b10 %
b10 $
#3
1!
b1000 &
0"
b11 #
b11 %
b11 $
#4
0!
1"
b1000 &
b100 #
b100 %
b100 $
#5
1!
b1000 &
0"
b101 #
b101 %
b101 $
#6
0"
b1000 &
b110 #
b110 %
b110 $
#7
0!
1"
b1000 &
b111 #
b111 %
b111 $
#8
b1000 &
1"
b1000 #
b1000 %
b1000 $
#9
1!
b1000 &
0"
b1001 #
b1001 %
b1001 $
#10
0"
b1000 &
b1010 #
b1010 %
b1010 $
#11
0!
1"
b1000 &
b1011 #
b1011 %
b1011 $
#12
1!
b1000 &
0"
b1100 #
b1100 %
b1100 $
#13
0!
1"
b1000 &
b1101 #
b1101 %
b1101 $
#14
b1000 &
1"
b1110 #
b1110 %
b1110 $
#15
1!
b1000 &
0"
b1111 #
b1111 %
b1111 $
#16
0!
1"
b1000 &
b10000 #
b10000 %
b10000 $
#17
1!
b1000 &
0"
b10001 #
b10001 %
b10001 $
#18
0"
b1000 &
b10010 #
b10010 %
b10010 $
#19
0!
1"
b1000 &
b10011 #
b10011 %
b10011 $
#20
1!
b1000 &
0"
b10100 #
b10100 %
b10100 $
#21
0!
1"
b1000 &
b10101 #
b10101 %
b10101 $
#22
b1000 &
1"
b10110 #
b10110 %
b10110 $
#23
1!
b1000 &
0"
b10111 #
b10111 %
b10111 $
#24
0"
b1000 &
b11000 #
b11000 %
b11000 $
#25
0!
1"
b1000 &
b11001 #
b11001 %
b11001 $
#26
b1000 &
1"
b11010 #
b11010 %
b11010 $
#27
1!
b1000 &
0"
b11011 #
b11011 %
b11011 $
#28
0!
1"
b1000 &
b11100 #
b11100 %
b11100 $
#29
1!
b1000 &
0"
b11101 #
b11101 %
b11101 $
#30
0"
b1000 &
b11110 #
b11110 %
b11110 $
#31
0!
1"
b1000 &
b11111 #
b11111 %
b11111 $
#32
b1000 &
1"
b100000 #
b100000 %
b100000 $
#33
1!
b1000 &
0"
b100001 #
b100001 %
b100001 $
#34
0"
b1000 &
b100010 #
b100010 %
b100010 $
#35
0!
1"
b1000 &
b100011 #
b100011 %
b100011 $
#36
1!
b1000 &
0"
b100100 #
b100100 %
b100100 $
#37
0!
1"
b1000 &
b100101 #
b100101 %
b100101 $
#38
b1000 &
1"
b100110 #
b100110 %
b100110 $
#39
1!
b1000 &
0"
b100111 #
b100111 %
b100111 $
#40
0"
b1000 &
b101000 #
b101000 %
b101000 $
#41
0!
1"
b1000 &
b101001 #
b101001 %
b101001 $
#42
b1000 &
1"
b101010 #
b101010 %
b101010 $
#43
1!
b1000 &
0"
b101011 #
b101011 %
b101011 $
#44
0!
1"
b1000 &
b101100 #
b101100 %
b101100 $
#45
1!
b1000 &
0"
b101101 #
b101101 %
b101101 $
#46
0"
b1000 &
b101110 #
b101110 %
b101110 $
#47
0!
1"
b1000 &
b101111 #
b101111 %
b101111 $
#48
1!
b1000 &
0"
b110000 #
b110000 %
b110000 $
#49
0!
1"
b1000 &
b110001 #
b110001 %
b110001 $
#50
b1000 &
1"
b110010 #
b110010 %
b110010 $
#51
1!
b1000 &
0"
b110011 #
b110011 %
b110011 $
#52
0!
1"
b1000 &
b110100 #
b110100 %
b110100 $
#53
1!
b1000 &
0"
b110101 #
b110101 %
b110101 $
#54
0"
b1000 &
b110110 #
b110110 %
b110110 $
#55
0!
1"
b1000 &
b110111 #
b110111 %
b110111 $
#56
b1000 &
1"
b111000 #
b111000 %
b111000 $
#57
1!
b1000 &
0"
b111001 #
b111001 %
b111001 $
#58
0"
b1000 &
b111010 #
b111010 %
b111010 $
#59
0!
1"
b1000 &
b111011 #
b111011 %
b111011 $
#60
1!
b1000 &
0"
b111100 #
b111100 %
b111100 $
#61
0!
1"
b1000 &
b111101 #
b111101 %
b111101 $
#62
b1000 &
1"
b111110 #
b111110 %
b111110 $
#63
1!
b1000 &
0"
b111111 #
b111111 %
b111111 $
#64
0!
1"
b1000 &
b1000000 #
b1000000 %
b1000000 $
#65
1!
b1000 &
0"
b1000001 #
b1000001 %
b1000001 $
#66
0"
b1000 &
b1000010 #
b1000010 %
b1000010 $
#67
0!
1"
b1000 &
b1000011 #
b1000011 %
b1000011 $
#68
1!
b1000 &
0"
b1000100 #
b1000100 %
b1000100 $
#69
0!
1"
b1000 &
b1000101 #
b1000101 %
b1000101 $
#70
b1000 &
1"
b1000110 #
b1000110 %
b1000110 $
#71
1!
b1000 &
0"
b1000111 #
b1000111 %
b1000111 $
#72
0"
b1000 &
b1001000 #
b1001000 %
b1001000 $
#73
0!
1"
b1000 &
b1001001 #
b1001001 %
b1001001 $
#74
b1000 &
1"
b1001010 #
b1001010 %
b1001010 $
#75
1!
b1000 &
0"
b1001011 #
b1001011 %
b1001011 $
#76
0!
1"
b1000 &
b1001100 #
b1001100 %
b1001100 $
#77
1!
b1000 &
0"
b1001101 #
b1001101 %
b1001101 $
#78
0"
b1000 &
b1001110 #
b1001110 %
b1001110 $
#79
0!
1"
b1000 &
b1001111 #
b1001111 %
b1001111 $
#80
1!
b1000 &
0"
b1010000 #
b1010000 %
b1010000 $
#81
0!
1"
b1000 &
b1010001 #
b1010001 %
b1010001 $
#82
b1000 &
1"
b1010010 #
b1010010 %
b1010010 $
#83
1!
b1000 &
0"
b1010011 #
b1010011 %
b1010011 $
#84
0!
1"
b1000 &
b1010100 #
b1010100 %
b1010100 $
#85
1!
b1000 &
0"
b1010101 #
b1010101 %
b1010101 $
#86
0"
b1000 &
b1010110 #
b1010110 %
b1010110 $
#87
0!
1"
b1000 &
b1010111 #
b1010111 %
b1010111 $
#88
b1000 &
1"
b1011000 #
b1011000 %
b1011000 $
#89
1!
b1000 &
0"
b1011001 #
b1011001 %
b1011001 $
#90
0"
b1000 &
b1011010 #
b1011010 %
b1011010 $
#91
0!
1"
b1000 &
b1011011 #
b1011011 %
b1011011 $
#92
1!
b1000 &
0"
b1011100 #
b1011100 %
b1011100 $
#93
0!
1"
b1000 &
b1011101 #
b1011101 %
b1011101 $
#94
b1000 &
1"
b1011110 #
b1011110 %
b1011110 $
#95
1!
b1000 &
0"
b1011111 #
b1011111 %
b1011111 $
#96
0"
b1000 &
b1100000 #
b1100000 %
b1100000 $
#97
0!
1"
b1000 &
b1100001 #
b1100001 %
b1100001 $
#98
b1000 &
1"
b1100010 #
b1100010 %
b1100010 $
#99
1!
b1000 &
0"
b1100011 #
b1100011 %
b1100011 $
#100
0!
1"
b1000 &
b1100100 #
b1100100 %
b1100100 $
#101
1!
b1000 &
0"
b1100101 #
b1100101 %
b1100101 $
#102
0"
b1000 &
b1100110 #
b1100110 %
b1100110 $
#103
0!
1"
b1000 &
b1100111 #
b1100111 %
b1100111 $
#104
b1000 &
1"
b1101000 #
b1101000 %
b1101000 $
#105
1!
b1000 &
0"
b1101001 #
b1101001 %
b1101001 $
#106
0"
b1000 &
b1101010 #
b1101010 %
b1101010 $
#107
0!
1"
b1000 &
b1101011 #
b1101011 %
b1101011 $
#108
1!
b1000 &
0"
b1101100 #
b1101100 %
b1101100 $
#109
0!
1"
b1000 &
b1101101 #
b1101101 %
b1101101 $
#110
b1000 &
1"
b1101110 #
b1101110 %
b1101110 $
#111
1!
b1000 &
0"
b1101111 #
b1101111 %
b1101111 $
#112
0!
1"
b1000 &
b1110000 #
b1110000 %
b1110000 $
#113
1!
b1000 &
0"
b1110001 #
b1110001 %
b1110001 $
#114
0"
b1000 &
b1110010 #
b1110010 %
b1110010 $
#115
0!
1"
b1000 &
b1110011 #
b1110011 %
b1110011 $
#116
1!
b1000 &
0"
b1110100 #
b1110100 %
b1110100 $
#117
0!
1"
b1000 &
b1110101 #
b1110101 %
b1110101 $
#118
b1000 &
1"
b1110110 #
b1110110 %
b1110110 $
#119
1!
b1000 &
0"
b1110111 #
b1110111 %
b1110111 $
#120
0"
b1000 &
b1111000 #
b1111000 %
b1111000 $
#121
0!
1"
b1000 &
b1111001 #
b1111001 %
b1111001 $
#122
b1000 &
1"
b1111010 #
b1111010 %
b1111010 $
#123
1!
b1000 &
0"
b1111011 #
b1111011 %
b1111011 $
#124
0!
1"
b1000 &
b1111100 #
b1111100 %
b1111100 $
#125
1!
b1000 &
0"
b1111101 #
b1111101 %
b1111101 $
#126
0"
b1000 &
b1111110 #
b1111110 %
b1111110 $
#127
0!
1"
b1000 &
b1111111 #
b1111111 %
b1111111 $
#128
b1000 &
1"
b10000000 #
b10000000 %
b10000000 $
#129
1!
b1000 &
0"
b10000001 #
b10000001 %
b10000001 $
#130
0"
b1000 &
b10000010 #
b10000010 %
b10000010 $
#131
0!
1"
b1000 &
b10000011 #
b10000011 %
b10000011 $
#132
1!
b1000 &
0"
b10000100 #
b10000100 %
b10000100 $
#133
0!
1"
b1000 &
b10000101 #
b10000101 %
b10000101 $
#134
b1000 &
1"
b10000110 #
b10000110 %
b10000110 $
#135
1!
b1000 &
0"
b10000111 #
b10000111 %
b10000111 $
#136
0"
b1000 &
b10001000 #
b10001000 %
b10001000 $
#137
0!
1"
b1000 &
b10001001 #
b10001001 %
b10001001 $
#138
b1000 &
1"
b10001010 #
b10001010 %
b10001010 $
#139
1!
b1000 &
0"
b10001011 #
b10001011 %
b10001011 $
#140
0!
1"
b1000 &
b10001100 #
b10001100 %
b10001100 $
#141
1!
b1000 &
0"
b10001101 #
b10001101 %
b10001101 $
#142
0"
b1000 &
b10001110 #
b10001110 %
b10001110 $
#143
0!
1"
b1000 &
b10001111 #
b10001111 %
b10001111 $
#144
1!
b1000 &
0"
b10010000 #
b10010000 %
b10010000 $
#145
0!
1"
b1000 &
b10010001 #
b10010001 %
b10010001 $
#146
b1000 &
1"
b10010010 #
b10010010 %
b10010010 $
#147
1!
b1000 &
0"
b10010011 #
b10010011 %
b10010011 $
#148
0!
1"
b1000 &
b10010100 #
b10010100 %
b10010100 $
#149
1!
b1000 &
0"
b10010101 #
b10010101 %
b10010101 $
#150
0"
b1000 &
b10010110 #
b10010110 %
b10010110 $
#151
0!
1"
b1000 &
b10010111 #
b10010111 %
b10010111 $
#152
b1000 &
1"
b10011000 #
b10011000 %
b10011000 $
#153
1!
b1000 &
0"
b10011001 #
b10011001 %
b10011001 $
#154
0"
b1000 &
b10011010 #
b10011010 %
b10011010 $
#155
0!
1"
b1000 &
b10011011 #
b10011011 %
b10011011 $
#156
1!
b1000 &
0"
b10011100 #
b10011100 %
b10011100 $
#157
0!
1"
b1000 &
b10011101 #
b10011101 %
b10011101 $
#158
b1000 &
1"
b10011110 #
b10011110 %
b10011110 $
#159
1!
b1000 &
0"
b10011111 #
b10011111 %
b10011111 $
#160
0"
b1000 &
b10100000 #
b10100000 %
b10100000 $
#161
0!
1"
b1000 &
b10100001 #
b10100001 %
b10100001 $
#162
b1000 &
1"
b10100010 #
b10100010 %
b10100010 $
#163
1!
b1000 &
0"
b10100011 #
b10100011 %
b10100011 $
#164
0!
1"
b1000 &
b10100100 #
b10100100 %
b10100100 $
#165
1!
b1000 &
0"
b10100101 #
b10100101 %
b10100101 $
#166
0"
b1000 &
b10100110 #
b10100110 %
b10100110 $
#167
0!
1"
b1000 &
b10100111 #
b10100111 %
b10100111 $
#168
b1000 &
1"
b10101000 #
b10101000 %
b10101000 $
#169
1!
b1000 &
0"
b10101001 #
b10101001 %
b10101001 $
#170
0"
b1000 &
b10101010 #
b10101010 %
b10101010 $
#171
0!
1"
b1000 &
b10101011 #
b10101011 %
b10101011 $
#172
1!
b1000 &
0"
b10101100 #
b10101100 %
b10101100 $
#173
0!
1"
b1000 &
b10101101 #
b10101101 %
b10101101 $
#174
b1000 &
1"
b10101110 #
b10101110 %
b10101110 $
#175
1!
b1000 &
0"
b10101111 #
b10101111 %
b10101111 $
#176
0!
1"
b1000 &
b10110000 #
b10110000 %
b10110000 $
#177
1!
b1000 &
0"
b10110001 #
b10110001 %
b10110001 $
#178
0"
b1000 &
b10110010 #
b10110010 %
b10110010 $
#179
0!
1"
b1000 &
b10110011 #
b10110011 %
b10110011 $
#180
1!
b1000 &
0"
b10110100 #
b10110100 %
b10110100 $
#181
0!
1"
b1000 &
b10110101 #
b10110101 %
b10110101 $
#182
b1000 &
1"
b10110110 #
b10110110 %
b10110110 $
#183
1!
b1000 &
0"
b10110111 #
b10110111 %
b10110111 $
#184
0"
b1000 &
b10111000 #
b10111000 %
b10111000 $
#185
0!
1"
b1000 &
b10111001 #
b10111001 %
b10111001 $
#186
b1000 &
1"
b10111010 #
b10111010 %
b10111010 $
#187
1!
b1000 &
0"
b10111011 #
b10111011 %
b10111011 $
#188
0!
1"
b1000 &
b10111100 #
b10111100 %
b10111100 $
#189
1!
b1000 &
0"
b10111101 #
b10111101 %
b10111101 $
#190
0"
b1000 &
b10111110 #
b10111110 %
b10111110 $
#191
0!
1"
b1000 &
b10111111 #
b10111111 %
b10111111 $
#192
1!
b1000 &
0"
b11000000 #
b11000000 %
b11000000 $
#193
0!
1"
b1000 &
b11000001 #
b11000001 %
b11000001 $
#194
b1000 &
1"
b11000010 #
b11000010 %
b11000010 $
#195
1!
b1000 &
0"
b11000011 #
b11000011 %
b11000011 $
#196
0!
1"
b1000 &
b11000100 #
b11000100 %
b11000100 $
#197
1!
b1000 &
0"
b11000101 #
b11000101 %
b11000101 $
#198
0"
b1000 &
b11000110 #
b11000110 %
b11000110 $
#199
0!
1"
b1000 &
b11000111 #
b11000111 %
b11000111 $
#200
b1000 &
1"
b11001000 #
b11001000 %
b11001000 $
#201
1!
b1000 &
0"
b11001001 #
b11001001 %
b11001001 $
#202
0"
b1000 &
b11001010 #
b11001010 %
b11001010 $
#203
0!
1"
b1000 &
b11001011 #
b11001011 %
b11001011 $
#204
1!
b1000 &
0"
b11001100 #
b11001100 %
b11001100 $
#205
0!
1"
b1000 &
b11001101 #
b11001101 %
b11001101 $
#206
b1000 &
1"
b11001110 #
b11001110 %
b11001110 $
#207
1!
b1000 &
0"
b11001111 #
b11001111 %
b11001111 $
#208
0!
1"
b1000 &
b11010000 #
b11010000 %
b11010000 $
#209
1!
b1000 &
0"
b11010001 #
b11010001 %
b11010001 $
#210
0"
b1000 &
b11010010 #
b11010010 %
b11010010 $
#211
0!
1"
b1000 &
b11010011 #
b11010011 %
b11010011 $
#212
1!
b1000 &
0"
b11010100 #
b11010100 %
b11010100 $
#213
0!
1"
b1000 &
b11010101 #
b11010101 %
b11010101 $
#214
b1000 &
1"
b11010110 #
b11010110 %
b11010110 $
#215
1!
b1000 &
0"
b11010111 #
b11010111 %
b11010111 $
#216
0"
b1000 &
b11011000 #
b11011000 %
b11011000 $
#217
0!
1"
b1000 &
b11011001 #
b11011001 %
b11011001 $
#218
b1000 &
1"
b11011010 #
b11011010 %
b11011010 $
#219
1!
b1000 &
0"
b11011011 #
b11011011 %
b11011011 $
#220
0!
1"
b1000 &
b11011100 #
b11011100 %
b11011100 $
#221
1!
b1000 &
0"
b11011101 #
b11011101 %
b11011101 $
#222
0"
b1000 &
b11011110 #
b11011110 %
b11011110 $
#223
0!
1"
b1000 &
b11011111 #
b11011111 %
b11011111 $
#224
b1000 &
1"
b11100000 #
b11100000 %
b11100000 $
#225
1!
b1000 &
0"
b11100001 #
b11100001 %
b11100001 $
#226
0"
b1000 &
b11100010 #
b11100010 %
b11100010 $
#227
0!
1"
b1000 &
b11100011 #
b11100011 %
b11100011 $
#228
1!
b1000 &
0"
b11100100 #
b11100100 %
b11100100 $
#229
0!
1"
b1000 &
b11100101 #
b11100101 %
b11100101 $
#230
b1000 &
1"
b11100110 #
b11100110 %
b11100110 $
#231
1!
b1000 &
0"
b11100111 #
b11100111 %
b11100111 $
#232
0"
b1000 &
b11101000 #
b11101000 %
b11101000 $
#233
0!
1"
b1000 &
b11101001 #
b11101001 %
b11101001 $
#234
b1000 &
1"
b11101010 #
b11101010 %
b11101010 $
#235
1!
b1000 &
0"
b11101011 #
b11101011 %
b11101011 $
#236
0!
1"
b1000 &
b11101100 #
b11101100 %
b11101100 $
#237
1!
b1000 &
0"
b11101101 #
b11101101 %
b11101101 $
#238
0"
b1000 &
b11101110 #
b11101110 %
b11101110 $
#239
0!
1"
b1000 &
b11101111 #
b11101111 %
b11101111 $
#240
1!
b1000 &
0"
b11110000 #
b11110000 %
b11110000 $
#241
0!
1"
b1000 &
b11110001 #
b11110001 %
b11110001 $
#242
b1000 &
1"
b11110010 #
b11110010 %
b11110010 $
#243
1!
b1000 &
0"
b11110011 #
b11110011 %
b11110011 $
#244
0!
1"
b1000 &
b11110100 #
b11110100 %
b11110100 $
#245
1!
b1000 &
0"
b11110101 #
b11110101 %
b11110101 $
#246
0"
b1000 &
b11110110 #
b11110110 %
b11110110 $
#247
0!
1"
b1000 &
b11110111 #
b11110111 %
b11110111 $
#248
b1000 &
1"
b11111000 #
b11111000 %
b11111000 $
#249
1!
b1000 &
0"
b11111001 #
b11111001 %
b11111001 $
#250
0"
b1000 &
b11111010 #
b11111010 %
b11111010 $
#251
0!
1"
b1000 &
b11111011 #
b11111011 %
b11111011 $
#252
1!
b1000 &
0"
b11111100 #
b11111100 %
b11111100 $
#253
0!
1"
b1000 &
b11111101 #
b11111101 %
b11111101 $
#254
b1000 &
1"
b11111110 #
b11111110 %
b11111110 $
#255
b11111111 $
