Day20_adder&sub_beh/fbit_adder_sub.v
module fbit_adder_sub (
	input [3:0]a_in ,
	input [3:0]b_in ,
	output reg [3:0]out,
	output reg carry_out,
	output reg borrow_out,
	input mode 
);

always @(*) begin

	carry_out = 0 ; borrow_out = 0;

	case(mode)
		1 : begin
			{carry_out,out} = a_in + b_in ;
		end
		
		0 : begin
			out = a_in - b_in ;
			borrow_out = (a_in<b_in) ? 1 : 0 ;
		end
	endcase
end

endmodule

Day20_adder&sub_beh/tb_fbit_adder_sub.v
module tb_fbit_adder_sub ;

reg [3:0] tb_a_in ;
reg [3:0] tb_b_in ;
reg       tb_mode ;
wire [3:0] tb_out ;
wire       tb_carry_out ;
wire       tb_borrow_out ;
integer i,j,k ;

fbit_adder_sub dut (
    .a_in(tb_a_in),
    .b_in(tb_b_in),
    .out(tb_out),
    .carry_out(tb_carry_out),
    .borrow_out(tb_borrow_out),
    .mode(tb_mode)
);

initial begin

    for(i = 0; i < 16; i = i + 1) begin
        for(j = 0; j < 16; j = j + 1) begin
            for( k = 0; k < 2; k = k + 1) begin

                tb_a_in = i;
                tb_b_in = j;
                tb_mode = k;
                #10;

            end
        end
    end

    $finish;   
end

initial begin 
    $dumpfile("tb_fbit_adder_sub.vcd");
    $dumpvars(0, tb_fbit_adder_sub);
end

endmodule

Day20_adder&sub_beh/tb_fbit_adder_sub.vcd
$date
	Tue Nov 11 06:02:35 2025
$end
$version
	Icarus Verilog
$end
$timescale
	1s
$end
$scope module tb_fbit_adder_sub $end
$var wire 4 ! tb_out [3:0] $end
$var wire 1 " tb_carry_out $end
$var wire 1 # tb_borrow_out $end
$var reg 4 $ tb_a_in [3:0] $end
$var reg 4 % tb_b_in [3:0] $end
$var reg 1 & tb_mode $end
$var integer 32 ' i [31:0] $end
$var integer 32 ( j [31:0] $end
$var integer 32 ) k [31:0] $end
$scope module dut $end
$var wire 4 * a_in [3:0] $end
$var wire 4 + b_in [3:0] $end
$var wire 1 & mode $end
$var reg 1 # borrow_out $end
$var reg 1 " carry_out $end
$var reg 4 , out [3:0] $end
$upscope $end
$upscope $end
$enddefinitions $end
#0
$dumpvars
b0 ,
b0 +
b0 *
b0 )
b0 (
b0 '
0&
b0 %
b0 $
0#
0"
b0 !
$end
#10
1&
b1 )
#20
1#
b1111 !
b1111 ,
0&
b1 %
b1 +
b1 (
b0 )
#30
b1 !
b1 ,
0#
1&
b1 )
#40
1#
b1110 !
b1110 ,
0&
b10 %
b10 +
b10 (
b0 )
#50
b10 !
b10 ,
0#
1&
b1 )
#60
1#
b1101 !
b1101 ,
0&
b11 %
b11 +
b11 (
b0 )
#70
b11 !
b11 ,
0#
1&
b1 )
#80
1#
b1100 !
b1100 ,
0&
b100 %
b100 +
b100 (
b0 )
#90
b100 !
b100 ,
0#
1&
b1 )
#100
1#
b1011 !
b1011 ,
0&
b101 %
b101 +
b101 (
b0 )
#110
b101 !
b101 ,
0#
1&
b1 )
#120
1#
b1010 !
b1010 ,
0&
b110 %
b110 +
b110 (
b0 )
#130
b110 !
b110 ,
0#
1&
b1 )
#140
1#
b1001 !
b1001 ,
0&
b111 %
b111 +
b111 (
b0 )
#150
b111 !
b111 ,
0#
1&
b1 )
#160
1#
b1000 !
b1000 ,
0&
b1000 %
b1000 +
b1000 (
b0 )
#170
0#
1&
b1 )
#180
1#
b111 !
b111 ,
0&
b1001 %
b1001 +
b1001 (
b0 )
#190
b1001 !
b1001 ,
0#
1&
b1 )
#200
1#
b110 !
b110 ,
0&
b1010 %
b1010 +
b1010 (
b0 )
#210
b1010 !
b1010 ,
0#
1&
b1 )
#220
1#
b101 !
b101 ,
0&
b1011 %
b1011 +
b1011 (
b0 )
#230
b1011 !
b1011 ,
0#
1&
b1 )
#240
1#
b100 !
b100 ,
0&
b1100 %
b1100 +
b1100 (
b0 )
#250
b1100 !
b1100 ,
0#
1&
b1 )
#260
1#
b11 !
b11 ,
0&
b1101 %
b1101 +
b1101 (
b0 )
#270
b1101 !
b1101 ,
0#
1&
b1 )
#280
1#
b10 !
b10 ,
0&
b1110 %
b1110 +
b1110 (
b0 )
#290
b1110 !
b1110 ,
0#
1&
b1 )
#300
1#
b1 !
b1 ,
0&
b1111 %
b1111 +
b1111 (
b0 )
#310
b1111 !
b1111 ,
0#
1&
b1 )
#320
b1 !
b1 ,
0&
b0 %
b0 +
b1 $
b1 *
b1 '
b0 (
b0 )
#330
1&
b1 )
#340
b0 !
b0 ,
0&
b1 %
b1 +
b1 (
b0 )
#350
b10 !
b10 ,
1&
b1 )
#360
1#
b1111 !
b1111 ,
0&
b10 %
b10 +
b10 (
b0 )
#370
b11 !
b11 ,
0#
1&
b1 )
#380
1#
b1110 !
b1110 ,
0&
b11 %
b11 +
b11 (
b0 )
#390
b100 !
b100 ,
0#
1&
b1 )
#400
1#
b1101 !
b1101 ,
0&
b100 %
b100 +
b100 (
b0 )
#410
b101 !
b101 ,
0#
1&
b1 )
#420
1#
b1100 !
b1100 ,
0&
b101 %
b101 +
b101 (
b0 )
#430
b110 !
b110 ,
0#
1&
b1 )
#440
1#
b1011 !
b1011 ,
0&
b110 %
b110 +
b110 (
b0 )
#450
b111 !
b111 ,
0#
1&
b1 )
#460
1#
b1010 !
b1010 ,
0&
b111 %
b111 +
b111 (
b0 )
#470
b1000 !
b1000 ,
0#
1&
b1 )
#480
1#
b1001 !
b1001 ,
0&
b1000 %
b1000 +
b1000 (
b0 )
#490
0#
1&
b1 )
#500
1#
b1000 !
b1000 ,
0&
b1001 %
b1001 +
b1001 (
b0 )
#510
b1010 !
b1010 ,
0#
1&
b1 )
#520
1#
b111 !
b111 ,
0&
b1010 %
b1010 +
b1010 (
b0 )
#530
b1011 !
b1011 ,
0#
1&
b1 )
#540
1#
b110 !
b110 ,
0&
b1011 %
b1011 +
b1011 (
b0 )
#550
b1100 !
b1100 ,
0#
1&
b1 )
#560
1#
b101 !
b101 ,
0&
b1100 %
b1100 +
b1100 (
b0 )
#570
b1101 !
b1101 ,
0#
1&
b1 )
#580
1#
b100 !
b100 ,
0&
b1101 %
b1101 +
b1101 (
b0 )
#590
b1110 !
b1110 ,
0#
1&
b1 )
#600
1#
b11 !
b11 ,
0&
b1110 %
b1110 +
b1110 (
b0 )
#610
b1111 !
b1111 ,
0#
1&
b1 )
#620
1#
b10 !
b10 ,
0&
b1111 %
b1111 +
b1111 (
b0 )
#630
1"
b0 !
b0 ,
0#
1&
b1 )
#640
b10 !
b10 ,
0"
0&
b0 %
b0 +
b10 $
b10 *
b10 '
b0 (
b0 )
#650
1&
b1 )
#660
b1 !
b1 ,
0&
b1 %
b1 +
b1 (
b0 )
#670
b11 !
b11 ,
1&
b1 )
#680
b0 !
b0 ,
0&
b10 %
b10 +
b10 (
b0 )
#690
b100 !
b100 ,
1&
b1 )
#700
1#
b1111 !
b1111 ,
0&
b11 %
b11 +
b11 (
b0 )
#710
b101 !
b101 ,
0#
1&
b1 )
#720
1#
b1110 !
b1110 ,
0&
b100 %
b100 +
b100 (
b0 )
#730
b110 !
b110 ,
0#
1&
b1 )
#740
1#
b1101 !
b1101 ,
0&
b101 %
b101 +
b101 (
b0 )
#750
b111 !
b111 ,
0#
1&
b1 )
#760
1#
b1100 !
b1100 ,
0&
b110 %
b110 +
b110 (
b0 )
#770
b1000 !
b1000 ,
0#
1&
b1 )
#780
1#
b1011 !
b1011 ,
0&
b111 %
b111 +
b111 (
b0 )
#790
b1001 !
b1001 ,
0#
1&
b1 )
#800
1#
b1010 !
b1010 ,
0&
b1000 %
b1000 +
b1000 (
b0 )
#810
0#
1&
b1 )
#820
1#
b1001 !
b1001 ,
0&
b1001 %
b1001 +
b1001 (
b0 )
#830
b1011 !
b1011 ,
0#
1&
b1 )
#840
1#
b1000 !
b1000 ,
0&
b1010 %
b1010 +
b1010 (
b0 )
#850
b1100 !
b1100 ,
0#
1&
b1 )
#860
1#
b111 !
b111 ,
0&
b1011 %
b1011 +
b1011 (
b0 )
#870
b1101 !
b1101 ,
0#
1&
b1 )
#880
1#
b110 !
b110 ,
0&
b1100 %
b1100 +
b1100 (
b0 )
#890
b1110 !
b1110 ,
0#
1&
b1 )
#900
1#
b101 !
b101 ,
0&
b1101 %
b1101 +
b1101 (
b0 )
#910
b1111 !
b1111 ,
0#
1&
b1 )
#920
1#
b100 !
b100 ,
0&
b1110 %
b1110 +
b1110 (
b0 )
#930
1"
b0 !
b0 ,
0#
1&
b1 )
#940
1#
b11 !
b11 ,
0"
0&
b1111 %
b1111 +
b1111 (
b0 )
#950
1"
b1 !
b1 ,
0#
1&
b1 )
#960
b11 !
b11 ,
0"
0&
b0 %
b0 +
b11 $
b11 *
b11 '
b0 (
b0 )
#970
1&
b1 )
#980
b10 !
b10 ,
0&
b1 %
b1 +
b1 (
b0 )
#990
b100 !
b100 ,
1&
b1 )
#1000
b1 !
b1 ,
0&
b10 %
b10 +
b10 (
b0 )
#1010
b101 !
b101 ,
1&
b1 )
#1020
b0 !
b0 ,
0&
b11 %
b11 +
b11 (
b0 )
#1030
b110 !
b110 ,
1&
b1 )
#1040
1#
b1111 !
b1111 ,
0&
b100 %
b100 +
b100 (
b0 )
#1050
b111 !
b111 ,
0#
1&
b1 )
#1060
1#
b1110 !
b1110 ,
0&
b101 %
b101 +
b101 (
b0 )
#1070
b1000 !
b1000 ,
0#
1&
b1 )
#1080
1#
b1101 !
b1101 ,
0&
b110 %
b110 +
b110 (
b0 )
#1090
b1001 !
b1001 ,
0#
1&
b1 )
#1100
1#
b1100 !
b1100 ,
0&
b111 %
b111 +
b111 (
b0 )
#1110
b1010 !
b1010 ,
0#
1&
b1 )
#1120
1#
b1011 !
b1011 ,
0&
b1000 %
b1000 +
b1000 (
b0 )
#1130
0#
1&
b1 )
#1140
1#
b1010 !
b1010 ,
0&
b1001 %
b1001 +
b1001 (
b0 )
#1150
b1100 !
b1100 ,
0#
1&
b1 )
#1160
1#
b1001 !
b1001 ,
0&
b1010 %
b1010 +
b1010 (
b0 )
#1170
b1101 !
b1101 ,
0#
1&
b1 )
#1180
1#
b1000 !
b1000 ,
0&
b1011 %
b1011 +
b1011 (
b0 )
#1190
b1110 !
b1110 ,
0#
1&
b1 )
#1200
1#
b111 !
b111 ,
0&
b1100 %
b1100 +
b1100 (
b0 )
#1210
b1111 !
b1111 ,
0#
1&
b1 )
#1220
1#
b110 !
b110 ,
0&
b1101 %
b1101 +
b1101 (
b0 )
#1230
1"
b0 !
b0 ,
0#
1&
b1 )
#1240
1#
b101 !
b101 ,
0"
0&
b1110 %
b1110 +
b1110 (
b0 )
#1250
1"
b1 !
b1 ,
0#
1&
b1 )
#1260
1#
b100 !
b100 ,
0"
0&
b1111 %
b1111 +
b1111 (
b0 )
#1270
1"
b10 !
b10 ,
0#
1&
b1 )
#1280
b100 !
b100 ,
0"
0&
b0 %
b0 +
b100 $
b100 *
b100 '
b0 (
b0 )
#1290
1&
b1 )
#1300
b11 !
b11 ,
0&
b1 %
b1 +
b1 (
b0 )
#1310
b101 !
b101 ,
1&
b1 )
#1320
b10 !
b10 ,
0&
b10 %
b10 +
b10 (
b0 )
#1330
b110 !
b110 ,
1&
b1 )
#1340
b1 !
b1 ,
0&
b11 %
b11 +
b11 (
b0 )
#1350
b111 !
b111 ,
1&
b1 )
#1360
b0 !
b0 ,
0&
b100 %
b100 +
b100 (
b0 )
#1370
b1000 !
b1000 ,
1&
b1 )
#1380
1#
b1111 !
b1111 ,
0&
b101 %
b101 +
b101 (
b0 )
#1390
b1001 !
b1001 ,
0#
1&
b1 )
#1400
1#
b1110 !
b1110 ,
0&
b110 %
b110 +
b110 (
b0 )
#1410
b1010 !
b1010 ,
0#
1&
b1 )
#1420
1#
b1101 !
b1101 ,
0&
b111 %
b111 +
b111 (
b0 )
#1430
b1011 !
b1011 ,
0#
1&
b1 )
#1440
1#
b1100 !
b1100 ,
0&
b1000 %
b1000 +
b1000 (
b0 )
#1450
0#
1&
b1 )
#1460
1#
b1011 !
b1011 ,
0&
b1001 %
b1001 +
b1001 (
b0 )
#1470
b1101 !
b1101 ,
0#
1&
b1 )
#1480
1#
b1010 !
b1010 ,
0&
b1010 %
b1010 +
b1010 (
b0 )
#1490
b1110 !
b1110 ,
0#
1&
b1 )
#1500
1#
b1001 !
b1001 ,
0&
b1011 %
b1011 +
b1011 (
b0 )
#1510
b1111 !
b1111 ,
0#
1&
b1 )
#1520
1#
b1000 !
b1000 ,
0&
b1100 %
b1100 +
b1100 (
b0 )
#1530
1"
b0 !
b0 ,
0#
1&
b1 )
#1540
1#
b111 !
b111 ,
0"
0&
b1101 %
b1101 +
b1101 (
b0 )
#1550
1"
b1 !
b1 ,
0#
1&
b1 )
#1560
1#
b110 !
b110 ,
0"
0&
b1110 %
b1110 +
b1110 (
b0 )
#1570
1"
b10 !
b10 ,
0#
1&
b1 )
#1580
1#
b101 !
b101 ,
0"
0&
b1111 %
b1111 +
b1111 (
b0 )
#1590
1"
b11 !
b11 ,
0#
1&
b1 )
#1600
b101 !
b101 ,
0"
0&
b0 %
b0 +
b101 $
b101 *
b101 '
b0 (
b0 )
#1610
1&
b1 )
#1620
b100 !
b100 ,
0&
b1 %
b1 +
b1 (
b0 )
#1630
b110 !
b110 ,
1&
b1 )
#1640
b11 !
b11 ,
0&
b10 %
b10 +
b10 (
b0 )
#1650
b111 !
b111 ,
1&
b1 )
#1660
b10 !
b10 ,
0&
b11 %
b11 +
b11 (
b0 )
#1670
b1000 !
b1000 ,
1&
b1 )
#1680
b1 !
b1 ,
0&
b100 %
b100 +
b100 (
b0 )
#1690
b1001 !
b1001 ,
1&
b1 )
#1700
b0 !
b0 ,
0&
b101 %
b101 +
b101 (
b0 )
#1710
b1010 !
b1010 ,
1&
b1 )
#1720
1#
b1111 !
b1111 ,
0&
b110 %
b110 +
b110 (
b0 )
#1730
b1011 !
b1011 ,
0#
1&
b1 )
#1740
1#
b1110 !
b1110 ,
0&
b111 %
b111 +
b111 (
b0 )
#1750
b1100 !
b1100 ,
0#
1&
b1 )
#1760
1#
b1101 !
b1101 ,
0&
b1000 %
b1000 +
b1000 (
b0 )
#1770
0#
1&
b1 )
#1780
1#
b1100 !
b1100 ,
0&
b1001 %
b1001 +
b1001 (
b0 )
#1790
b1110 !
b1110 ,
0#
1&
b1 )
#1800
1#
b1011 !
b1011 ,
0&
b1010 %
b1010 +
b1010 (
b0 )
#1810
b1111 !
b1111 ,
0#
1&
b1 )
#1820
1#
b1010 !
b1010 ,
0&
b1011 %
b1011 +
b1011 (
b0 )
#1830
1"
b0 !
b0 ,
0#
1&
b1 )
#1840
1#
b1001 !
b1001 ,
0"
0&
b1100 %
b1100 +
b1100 (
b0 )
#1850
1"
b1 !
b1 ,
0#
1&
b1 )
#1860
1#
b1000 !
b1000 ,
0"
0&
b1101 %
b1101 +
b1101 (
b0 )
#1870
1"
b10 !
b10 ,
0#
1&
b1 )
#1880
1#
b111 !
b111 ,
0"
0&
b1110 %
b1110 +
b1110 (
b0 )
#1890
1"
b11 !
b11 ,
0#
1&
b1 )
#1900
1#
b110 !
b110 ,
0"
0&
b1111 %
b1111 +
b1111 (
b0 )
#1910
1"
b100 !
b100 ,
0#
1&
b1 )
#1920
b110 !
b110 ,
0"
0&
b0 %
b0 +
b110 $
b110 *
b110 '
b0 (
b0 )
#1930
1&
b1 )
#1940
b101 !
b101 ,
0&
b1 %
b1 +
b1 (
b0 )
#1950
b111 !
b111 ,
1&
b1 )
#1960
b100 !
b100 ,
0&
b10 %
b10 +
b10 (
b0 )
#1970
b1000 !
b1000 ,
1&
b1 )
#1980
b11 !
b11 ,
0&
b11 %
b11 +
b11 (
b0 )
#1990
b1001 !
b1001 ,
1&
b1 )
#2000
b10 !
b10 ,
0&
b100 %
b100 +
b100 (
b0 )
#2010
b1010 !
b1010 ,
1&
b1 )
#2020
b1 !
b1 ,
0&
b101 %
b101 +
b101 (
b0 )
#2030
b1011 !
b1011 ,
1&
b1 )
#2040
b0 !
b0 ,
0&
b110 %
b110 +
b110 (
b0 )
#2050
b1100 !
b1100 ,
1&
b1 )
#2060
1#
b1111 !
b1111 ,
0&
b111 %
b111 +
b111 (
b0 )
#2070
b1101 !
b1101 ,
0#
1&
b1 )
#2080
1#
b1110 !
b1110 ,
0&
b1000 %
b1000 +
b1000 (
b0 )
#2090
0#
1&
b1 )
#2100
1#
b1101 !
b1101 ,
0&
b1001 %
b1001 +
b1001 (
b0 )
#2110
b1111 !
b1111 ,
0#
1&
b1 )
#2120
1#
b1100 !
b1100 ,
0&
b1010 %
b1010 +
b1010 (
b0 )
#2130
1"
b0 !
b0 ,
0#
1&
b1 )
#2140
1#
b1011 !
b1011 ,
0"
0&
b1011 %
b1011 +
b1011 (
b0 )
#2150
1"
b1 !
b1 ,
0#
1&
b1 )
#2160
1#
b1010 !
b1010 ,
0"
0&
b1100 %
b1100 +
b1100 (
b0 )
#2170
1"
b10 !
b10 ,
0#
1&
b1 )
#2180
1#
b1001 !
b1001 ,
0"
0&
b1101 %
b1101 +
b1101 (
b0 )
#2190
1"
b11 !
b11 ,
0#
1&
b1 )
#2200
1#
b1000 !
b1000 ,
0"
0&
b1110 %
b1110 +
b1110 (
b0 )
#2210
1"
b100 !
b100 ,
0#
1&
b1 )
#2220
1#
b111 !
b111 ,
0"
0&
b1111 %
b1111 +
b1111 (
b0 )
#2230
1"
b101 !
b101 ,
0#
1&
b1 )
#2240
b111 !
b111 ,
0"
0&
b0 %
b0 +
b111 $
b111 *
b111 '
b0 (
b0 )
#2250
1&
b1 )
#2260
b110 !
b110 ,
0&
b1 %
b1 +
b1 (
b0 )
#2270
b1000 !
b1000 ,
1&
b1 )
#2280
b101 !
b101 ,
0&
b10 %
b10 +
b10 (
b0 )
#2290
b1001 !
b1001 ,
1&
b1 )
#2300
b100 !
b100 ,
0&
b11 %
b11 +
b11 (
b0 )
#2310
b1010 !
b1010 ,
1&
b1 )
#2320
b11 !
b11 ,
0&
b100 %
b100 +
b100 (
b0 )
#2330
b1011 !
b1011 ,
1&
b1 )
#2340
b10 !
b10 ,
0&
b101 %
b101 +
b101 (
b0 )
#2350
b1100 !
b1100 ,
1&
b1 )
#2360
b1 !
b1 ,
0&
b110 %
b110 +
b110 (
b0 )
#2370
b1101 !
b1101 ,
1&
b1 )
#2380
b0 !
b0 ,
0&
b111 %
b111 +
b111 (
b0 )
#2390
b1110 !
b1110 ,
1&
b1 )
#2400
1#
b1111 !
b1111 ,
0&
b1000 %
b1000 +
b1000 (
b0 )
#2410
0#
1&
b1 )
#2420
1#
b1110 !
b1110 ,
0&
b1001 %
b1001 +
b1001 (
b0 )
#2430
1"
b0 !
b0 ,
0#
1&
b1 )
#2440
1#
b1101 !
b1101 ,
0"
0&
b1010 %
b1010 +
b1010 (
b0 )
#2450
1"
b1 !
b1 ,
0#
1&
b1 )
#2460
1#
b1100 !
b1100 ,
0"
0&
b1011 %
b1011 +
b1011 (
b0 )
#2470
1"
b10 !
b10 ,
0#
1&
b1 )
#2480
1#
b1011 !
b1011 ,
0"
0&
b1100 %
b1100 +
b1100 (
b0 )
#2490
1"
b11 !
b11 ,
0#
1&
b1 )
#2500
1#
b1010 !
b1010 ,
0"
0&
b1101 %
b1101 +
b1101 (
b0 )
#2510
1"
b100 !
b100 ,
0#
1&
b1 )
#2520
1#
b1001 !
b1001 ,
0"
0&
b1110 %
b1110 +
b1110 (
b0 )
#2530
1"
b101 !
b101 ,
0#
1&
b1 )
#2540
1#
b1000 !
b1000 ,
0"
0&
b1111 %
b1111 +
b1111 (
b0 )
#2550
1"
b110 !
b110 ,
0#
1&
b1 )
#2560
b1000 !
b1000 ,
0"
0&
b0 %
b0 +
b1000 $
b1000 *
b1000 '
b0 (
b0 )
#2570
1&
b1 )
#2580
b111 !
b111 ,
0&
b1 %
b1 +
b1 (
b0 )
#2590
b1001 !
b1001 ,
1&
b1 )
#2600
b110 !
b110 ,
0&
b10 %
b10 +
b10 (
b0 )
#2610
b1010 !
b1010 ,
1&
b1 )
#2620
b101 !
b101 ,
0&
b11 %
b11 +
b11 (
b0 )
#2630
b1011 !
b1011 ,
1&
b1 )
#2640
b100 !
b100 ,
0&
b100 %
b100 +
b100 (
b0 )
#2650
b1100 !
b1100 ,
1&
b1 )
#2660
b11 !
b11 ,
0&
b101 %
b101 +
b101 (
b0 )
#2670
b1101 !
b1101 ,
1&
b1 )
#2680
b10 !
b10 ,
0&
b110 %
b110 +
b110 (
b0 )
#2690
b1110 !
b1110 ,
1&
b1 )
#2700
b1 !
b1 ,
0&
b111 %
b111 +
b111 (
b0 )
#2710
b1111 !
b1111 ,
1&
b1 )
#2720
b0 !
b0 ,
0&
b1000 %
b1000 +
b1000 (
b0 )
#2730
1"
1&
b1 )
#2740
1#
b1111 !
b1111 ,
0"
0&
b1001 %
b1001 +
b1001 (
b0 )
#2750
1"
b1 !
b1 ,
0#
1&
b1 )
#2760
1#
b1110 !
b1110 ,
0"
0&
b1010 %
b1010 +
b1010 (
b0 )
#2770
1"
b10 !
b10 ,
0#
1&
b1 )
#2780
1#
b1101 !
b1101 ,
0"
0&
b1011 %
b1011 +
b1011 (
b0 )
#2790
1"
b11 !
b11 ,
0#
1&
b1 )
#2800
1#
b1100 !
b1100 ,
0"
0&
b1100 %
b1100 +
b1100 (
b0 )
#2810
1"
b100 !
b100 ,
0#
1&
b1 )
#2820
1#
b1011 !
b1011 ,
0"
0&
b1101 %
b1101 +
b1101 (
b0 )
#2830
1"
b101 !
b101 ,
0#
1&
b1 )
#2840
1#
b1010 !
b1010 ,
0"
0&
b1110 %
b1110 +
b1110 (
b0 )
#2850
1"
b110 !
b110 ,
0#
1&
b1 )
#2860
1#
b1001 !
b1001 ,
0"
0&
b1111 %
b1111 +
b1111 (
b0 )
#2870
1"
b111 !
b111 ,
0#
1&
b1 )
#2880
b1001 !
b1001 ,
0"
0&
b0 %
b0 +
b1001 $
b1001 *
b1001 '
b0 (
b0 )
#2890
1&
b1 )
#2900
b1000 !
b1000 ,
0&
b1 %
b1 +
b1 (
b0 )
#2910
b1010 !
b1010 ,
1&
b1 )
#2920
b111 !
b111 ,
0&
b10 %
b10 +
b10 (
b0 )
#2930
b1011 !
b1011 ,
1&
b1 )
#2940
b110 !
b110 ,
0&
b11 %
b11 +
b11 (
b0 )
#2950
b1100 !
b1100 ,
1&
b1 )
#2960
b101 !
b101 ,
0&
b100 %
b100 +
b100 (
b0 )
#2970
b1101 !
b1101 ,
1&
b1 )
#2980
b100 !
b100 ,
0&
b101 %
b101 +
b101 (
b0 )
#2990
b1110 !
b1110 ,
1&
b1 )
#3000
b11 !
b11 ,
0&
b110 %
b110 +
b110 (
b0 )
#3010
b1111 !
b1111 ,
1&
b1 )
#3020
b10 !
b10 ,
0&
b111 %
b111 +
b111 (
b0 )
#3030
1"
b0 !
b0 ,
1&
b1 )
#3040
b1 !
b1 ,
0"
0&
b1000 %
b1000 +
b1000 (
b0 )
#3050
1"
1&
b1 )
#3060
b0 !
b0 ,
0"
0&
b1001 %
b1001 +
b1001 (
b0 )
#3070
1"
b10 !
b10 ,
1&
b1 )
#3080
1#
b1111 !
b1111 ,
0"
0&
b1010 %
b1010 +
b1010 (
b0 )
#3090
1"
b11 !
b11 ,
0#
1&
b1 )
#3100
1#
b1110 !
b1110 ,
0"
0&
b1011 %
b1011 +
b1011 (
b0 )
#3110
1"
b100 !
b100 ,
0#
1&
b1 )
#3120
1#
b1101 !
b1101 ,
0"
0&
b1100 %
b1100 +
b1100 (
b0 )
#3130
1"
b101 !
b101 ,
0#
1&
b1 )
#3140
1#
b1100 !
b1100 ,
0"
0&
b1101 %
b1101 +
b1101 (
b0 )
#3150
1"
b110 !
b110 ,
0#
1&
b1 )
#3160
1#
b1011 !
b1011 ,
0"
0&
b1110 %
b1110 +
b1110 (
b0 )
#3170
1"
b111 !
b111 ,
0#
1&
b1 )
#3180
1#
b1010 !
b1010 ,
0"
0&
b1111 %
b1111 +
b1111 (
b0 )
#3190
1"
b1000 !
b1000 ,
0#
1&
b1 )
#3200
b1010 !
b1010 ,
0"
0&
b0 %
b0 +
b1010 $
b1010 *
b1010 '
b0 (
b0 )
#3210
1&
b1 )
#3220
b1001 !
b1001 ,
0&
b1 %
b1 +
b1 (
b0 )
#3230
b1011 !
b1011 ,
1&
b1 )
#3240
b1000 !
b1000 ,
0&
b10 %
b10 +
b10 (
b0 )
#3250
b1100 !
b1100 ,
1&
b1 )
#3260
b111 !
b111 ,
0&
b11 %
b11 +
b11 (
b0 )
#3270
b1101 !
b1101 ,
1&
b1 )
#3280
b110 !
b110 ,
0&
b100 %
b100 +
b100 (
b0 )
#3290
b1110 !
b1110 ,
1&
b1 )
#3300
b101 !
b101 ,
0&
b101 %
b101 +
b101 (
b0 )
#3310
b1111 !
b1111 ,
1&
b1 )
#3320
b100 !
b100 ,
0&
b110 %
b110 +
b110 (
b0 )
#3330
1"
b0 !
b0 ,
1&
b1 )
#3340
b11 !
b11 ,
0"
0&
b111 %
b111 +
b111 (
b0 )
#3350
1"
b1 !
b1 ,
1&
b1 )
#3360
b10 !
b10 ,
0"
0&
b1000 %
b1000 +
b1000 (
b0 )
#3370
1"
1&
b1 )
#3380
b1 !
b1 ,
0"
0&
b1001 %
b1001 +
b1001 (
b0 )
#3390
1"
b11 !
b11 ,
1&
b1 )
#3400
b0 !
b0 ,
0"
0&
b1010 %
b1010 +
b1010 (
b0 )
#3410
1"
b100 !
b100 ,
1&
b1 )
#3420
1#
b1111 !
b1111 ,
0"
0&
b1011 %
b1011 +
b1011 (
b0 )
#3430
1"
b101 !
b101 ,
0#
1&
b1 )
#3440
1#
b1110 !
b1110 ,
0"
0&
b1100 %
b1100 +
b1100 (
b0 )
#3450
1"
b110 !
b110 ,
0#
1&
b1 )
#3460
1#
b1101 !
b1101 ,
0"
0&
b1101 %
b1101 +
b1101 (
b0 )
#3470
1"
b111 !
b111 ,
0#
1&
b1 )
#3480
1#
b1100 !
b1100 ,
0"
0&
b1110 %
b1110 +
b1110 (
b0 )
#3490
1"
b1000 !
b1000 ,
0#
1&
b1 )
#3500
1#
b1011 !
b1011 ,
0"
0&
b1111 %
b1111 +
b1111 (
b0 )
#3510
1"
b1001 !
b1001 ,
0#
1&
b1 )
#3520
b1011 !
b1011 ,
0"
0&
b0 %
b0 +
b1011 $
b1011 *
b1011 '
b0 (
b0 )
#3530
1&
b1 )
#3540
b1010 !
b1010 ,
0&
b1 %
b1 +
b1 (
b0 )
#3550
b1100 !
b1100 ,
1&
b1 )
#3560
b1001 !
b1001 ,
0&
b10 %
b10 +
b10 (
b0 )
#3570
b1101 !
b1101 ,
1&
b1 )
#3580
b1000 !
b1000 ,
0&
b11 %
b11 +
b11 (
b0 )
#3590
b1110 !
b1110 ,
1&
b1 )
#3600
b111 !
b111 ,
0&
b100 %
b100 +
b100 (
b0 )
#3610
b1111 !
b1111 ,
1&
b1 )
#3620
b110 !
b110 ,
0&
b101 %
b101 +
b101 (
b0 )
#3630
1"
b0 !
b0 ,
1&
b1 )
#3640
b101 !
b101 ,
0"
0&
b110 %
b110 +
b110 (
b0 )
#3650
1"
b1 !
b1 ,
1&
b1 )
#3660
b100 !
b100 ,
0"
0&
b111 %
b111 +
b111 (
b0 )
#3670
1"
b10 !
b10 ,
1&
b1 )
#3680
b11 !
b11 ,
0"
0&
b1000 %
b1000 +
b1000 (
b0 )
#3690
1"
1&
b1 )
#3700
b10 !
b10 ,
0"
0&
b1001 %
b1001 +
b1001 (
b0 )
#3710
1"
b100 !
b100 ,
1&
b1 )
#3720
b1 !
b1 ,
0"
0&
b1010 %
b1010 +
b1010 (
b0 )
#3730
1"
b101 !
b101 ,
1&
b1 )
#3740
b0 !
b0 ,
0"
0&
b1011 %
b1011 +
b1011 (
b0 )
#3750
1"
b110 !
b110 ,
1&
b1 )
#3760
1#
b1111 !
b1111 ,
0"
0&
b1100 %
b1100 +
b1100 (
b0 )
#3770
1"
b111 !
b111 ,
0#
1&
b1 )
#3780
1#
b1110 !
b1110 ,
0"
0&
b1101 %
b1101 +
b1101 (
b0 )
#3790
1"
b1000 !
b1000 ,
0#
1&
b1 )
#3800
1#
b1101 !
b1101 ,
0"
0&
b1110 %
b1110 +
b1110 (
b0 )
#3810
1"
b1001 !
b1001 ,
0#
1&
b1 )
#3820
1#
b1100 !
b1100 ,
0"
0&
b1111 %
b1111 +
b1111 (
b0 )
#3830
1"
b1010 !
b1010 ,
0#
1&
b1 )
#3840
b1100 !
b1100 ,
0"
0&
b0 %
b0 +
b1100 $
b1100 *
b1100 '
b0 (
b0 )
#3850
1&
b1 )
#3860
b1011 !
b1011 ,
0&
b1 %
b1 +
b1 (
b0 )
#3870
b1101 !
b1101 ,
1&
b1 )
#3880
b1010 !
b1010 ,
0&
b10 %
b10 +
b10 (
b0 )
#3890
b1110 !
b1110 ,
1&
b1 )
#3900
b1001 !
b1001 ,
0&
b11 %
b11 +
b11 (
b0 )
#3910
b1111 !
b1111 ,
1&
b1 )
#3920
b1000 !
b1000 ,
0&
b100 %
b100 +
b100 (
b0 )
#3930
1"
b0 !
b0 ,
1&
b1 )
#3940
b111 !
b111 ,
0"
0&
b101 %
b101 +
b101 (
b0 )
#3950
1"
b1 !
b1 ,
1&
b1 )
#3960
b110 !
b110 ,
0"
0&
b110 %
b110 +
b110 (
b0 )
#3970
1"
b10 !
b10 ,
1&
b1 )
#3980
b101 !
b101 ,
0"
0&
b111 %
b111 +
b111 (
b0 )
#3990
1"
b11 !
b11 ,
1&
b1 )
#4000
b100 !
b100 ,
0"
0&
b1000 %
b1000 +
b1000 (
b0 )
#4010
1"
1&
b1 )
#4020
b11 !
b11 ,
0"
0&
b1001 %
b1001 +
b1001 (
b0 )
