Day22_4bit_comparator/fbit_comparator.v
module fbit_comparator (
    input  [3:0] a_in,
    input  [3:0] b_in,
    output reg a_eq_b,
    output reg a_gt_b,
    output reg a_lt_b
);

    always @(*) begin
        a_eq_b = (a_in == b_in);
        a_gt_b = (a_in >  b_in);
        a_lt_b = (a_in <  b_in);
    end

endmodule

Day22_4bit_comparator/tb_fbit_comparator.v
module tb_fbit_comparator;

reg  [3:0] tb_a_in;
reg  [3:0] tb_b_in;
wire tb_a_eq_b;
wire tb_a_gt_b;
wire tb_a_lt_b;

integer i, j;
fbit_comparator dut (
    .a_in(tb_a_in),
    .b_in(tb_b_in),
    .a_eq_b(tb_a_eq_b),
    .a_gt_b(tb_a_gt_b),
    .a_lt_b(tb_a_lt_b)
);

initial begin
    for(i = 0; i < 16; i = i + 1) begin
        for(j = 0; j < 16; j = j + 1) begin
            tb_a_in = i;
            tb_b_in = j;
            #5;
        end
    end
    $finish;
end

initial begin
    $monitor("time=%0t | A=%b B=%b | EQ=%b GT=%b LT=%b",
              $time, tb_a_in, tb_b_in, tb_a_eq_b, tb_a_gt_b, tb_a_lt_b);
end

initial begin
    $dumpfile("tb_fbit_comparator.vcd");
    $dumpvars(0, tb_fbit_comparator);
end

endmodule

Day22_4bit_comparator/tb_fbit_comparator.vcd
$date
	Tue Nov 11 08:43:01 2025
$end
$version
	Icarus Verilog
$end
$timescale
	1s
$end
$scope module tb_fbit_comparator $end
$var wire 1 ! tb_a_lt_b $end
$var wire 1 " tb_a_gt_b $end
$var wire 1 # tb_a_eq_b $end
$var reg 4 $ tb_a_in [3:0] $end
$var reg 4 % tb_b_in [3:0] $end
$var integer 32 & i [31:0] $end
$var integer 32 ' j [31:0] $end
$scope module dut $end
$var wire 4 ( a_in [3:0] $end
$var wire 4 ) b_in [3:0] $end
$var reg 1 # a_eq_b $end
$var reg 1 " a_gt_b $end
$var reg 1 ! a_lt_b $end
$upscope $end
$upscope $end
$enddefinitions $end
#0
$dumpvars
b0 )
b0 (
b0 '
b0 &
b0 %
b0 $
1#
0"
0!
$end
#5
1!
0#
b1 %
b1 )
b1 '
#10
b10 %
b10 )
b10 '
#15
b11 %
b11 )
b11 '
#20
b100 %
b100 )
b100 '
#25
b101 %
b101 )
b101 '
#30
b110 %
b110 )
b110 '
#35
b111 %
b111 )
b111 '
#40
b1000 %
b1000 )
b1000 '
#45
b1001 %
b1001 )
b1001 '
#50
b1010 %
b1010 )
b1010 '
#55
b1011 %
b1011 )
b1011 '
#60
b1100 %
b1100 )
b1100 '
#65
b1101 %
b1101 )
b1101 '
#70
b1110 %
b1110 )
b1110 '
#75
b1111 %
b1111 )
b1111 '
#80
0!
1"
b0 %
b0 )
b1 $
b1 (
b1 &
b0 '
#85
0"
1#
b1 %
b1 )
b1 '
#90
1!
0#
b10 %
b10 )
b10 '
#95
b11 %
b11 )
b11 '
#100
b100 %
b100 )
b100 '
#105
b101 %
b101 )
b101 '
#110
b110 %
b110 )
b110 '
#115
b111 %
b111 )
b111 '
#120
b1000 %
b1000 )
b1000 '
#125
b1001 %
b1001 )
b1001 '
#130
b1010 %
b1010 )
b1010 '
#135
b1011 %
b1011 )
b1011 '
#140
b1100 %
b1100 )
b1100 '
#145
b1101 %
b1101 )
b1101 '
#150
b1110 %
b1110 )
b1110 '
#155
b1111 %
b1111 )
b1111 '
#160
0!
1"
b0 %
b0 )
b10 $
b10 (
b10 &
b0 '
#165
b1 %
b1 )
b1 '
#170
0"
1#
b10 %
b10 )
b10 '
#175
1!
0#
b11 %
b11 )
b11 '
#180
b100 %
b100 )
b100 '
#185
b101 %
b101 )
b101 '
#190
b110 %
b110 )
b110 '
#195
b111 %
b111 )
b111 '
#200
b1000 %
b1000 )
b1000 '
#205
b1001 %
b1001 )
b1001 '
#210
b1010 %
b1010 )
b1010 '
#215
b1011 %
b1011 )
b1011 '
#220
b1100 %
b1100 )
b1100 '
#225
b1101 %
b1101 )
b1101 '
#230
b1110 %
b1110 )
b1110 '
#235
b1111 %
b1111 )
b1111 '
#240
0!
1"
b0 %
b0 )
b11 $
b11 (
b11 &
b0 '
#245
b1 %
b1 )
b1 '
#250
b10 %
b10 )
b10 '
#255
0"
1#
b11 %
b11 )
b11 '
#260
1!
0#
b100 %
b100 )
b100 '
#265
b101 %
b101 )
b101 '
#270
b110 %
b110 )
b110 '
#275
b111 %
b111 )
b111 '
#280
b1000 %
b1000 )
b1000 '
#285
b1001 %
b1001 )
b1001 '
#290
b1010 %
b1010 )
b1010 '
#295
b1011 %
b1011 )
b1011 '
#300
b1100 %
b1100 )
b1100 '
#305
b1101 %
b1101 )
b1101 '
#310
b1110 %
b1110 )
b1110 '
#315
b1111 %
b1111 )
b1111 '
#320
0!
1"
b0 %
b0 )
b100 $
b100 (
b100 &
b0 '
#325
b1 %
b1 )
b1 '
#330
b10 %
b10 )
b10 '
#335
b11 %
b11 )
b11 '
#340
0"
1#
b100 %
b100 )
b100 '
#345
1!
0#
b101 %
b101 )
b101 '
#350
b110 %
b110 )
b110 '
#355
b111 %
b111 )
b111 '
#360
b1000 %
b1000 )
b1000 '
#365
b1001 %
b1001 )
b1001 '
#370
b1010 %
b1010 )
b1010 '
#375
b1011 %
b1011 )
b1011 '
#380
b1100 %
b1100 )
b1100 '
#385
b1101 %
b1101 )
b1101 '
#390
b1110 %
b1110 )
b1110 '
#395
b1111 %
b1111 )
b1111 '
#400
0!
1"
b0 %
b0 )
b101 $
b101 (
b101 &
b0 '
#405
b1 %
b1 )
b1 '
#410
b10 %
b10 )
b10 '
#415
b11 %
b11 )
b11 '
#420
b100 %
b100 )
b100 '
#425
0"
1#
b101 %
b101 )
b101 '
#430
1!
0#
b110 %
b110 )
b110 '
#435
b111 %
b111 )
b111 '
#440
b1000 %
b1000 )
b1000 '
#445
b1001 %
b1001 )
b1001 '
#450
b1010 %
b1010 )
b1010 '
#455
b1011 %
b1011 )
b1011 '
#460
b1100 %
b1100 )
b1100 '
#465
b1101 %
b1101 )
b1101 '
#470
b1110 %
b1110 )
b1110 '
#475
b1111 %
b1111 )
b1111 '
#480
0!
1"
b0 %
b0 )
b110 $
b110 (
b110 &
b0 '
#485
b1 %
b1 )
b1 '
#490
b10 %
b10 )
b10 '
#495
b11 %
b11 )
b11 '
#500
b100 %
b100 )
b100 '
#505
b101 %
b101 )
b101 '
#510
0"
1#
b110 %
b110 )
b110 '
#515
1!
0#
b111 %
b111 )
b111 '
#520
b1000 %
b1000 )
b1000 '
#525
b1001 %
b1001 )
b1001 '
#530
b1010 %
b1010 )
b1010 '
#535
b1011 %
b1011 )
b1011 '
#540
b1100 %
b1100 )
b1100 '
#545
b1101 %
b1101 )
b1101 '
#550
b1110 %
b1110 )
b1110 '
#555
b1111 %
b1111 )
b1111 '
#560
0!
1"
b0 %
b0 )
b111 $
b111 (
b111 &
b0 '
#565
b1 %
b1 )
b1 '
#570
b10 %
b10 )
b10 '
#575
b11 %
b11 )
b11 '
#580
b100 %
b100 )
b100 '
#585
b101 %
b101 )
b101 '
#590
b110 %
b110 )
b110 '
#595
0"
1#
b111 %
b111 )
b111 '
#600
1!
0#
b1000 %
b1000 )
b1000 '
#605
b1001 %
b1001 )
b1001 '
#610
b1010 %
b1010 )
b1010 '
#615
b1011 %
b1011 )
b1011 '
#620
b1100 %
b1100 )
b1100 '
#625
b1101 %
b1101 )
b1101 '
#630
b1110 %
b1110 )
b1110 '
#635
b1111 %
b1111 )
b1111 '
#640
0!
1"
b0 %
b0 )
b1000 $
b1000 (
b1000 &
b0 '
#645
b1 %
b1 )
b1 '
#650
b10 %
b10 )
b10 '
#655
b11 %
b11 )
b11 '
#660
b100 %
b100 )
b100 '
#665
b101 %
b101 )
b101 '
#670
b110 %
b110 )
b110 '
#675
b111 %
b111 )
b111 '
#680
0"
1#
b1000 %
b1000 )
b1000 '
#685
1!
0#
b1001 %
b1001 )
b1001 '
#690
b1010 %
b1010 )
b1010 '
#695
b1011 %
b1011 )
b1011 '
#700
b1100 %
b1100 )
b1100 '
#705
b1101 %
b1101 )
b1101 '
#710
b1110 %
b1110 )
b1110 '
#715
b1111 %
b1111 )
b1111 '
#720
0!
1"
b0 %
b0 )
b1001 $
b1001 (
b1001 &
b0 '
#725
b1 %
b1 )
b1 '
#730
b10 %
b10 )
b10 '
#735
b11 %
b11 )
b11 '
#740
b100 %
b100 )
b100 '
#745
b101 %
b101 )
b101 '
#750
b110 %
b110 )
b110 '
#755
b111 %
b111 )
b111 '
#760
b1000 %
b1000 )
b1000 '
#765
0"
1#
b1001 %
b1001 )
b1001 '
#770
1!
0#
b1010 %
b1010 )
b1010 '
#775
b1011 %
b1011 )
b1011 '
#780
b1100 %
b1100 )
b1100 '
#785
b1101 %
b1101 )
b1101 '
#790
b1110 %
b1110 )
b1110 '
#795
b1111 %
b1111 )
b1111 '
#800
0!
1"
b0 %
b0 )
b1010 $
b1010 (
b1010 &
b0 '
#805
b1 %
b1 )
b1 '
#810
b10 %
b10 )
b10 '
#815
b11 %
b11 )
b11 '
#820
b100 %
b100 )
b100 '
#825
b101 %
b101 )
b101 '
#830
b110 %
b110 )
b110 '
#835
b111 %
b111 )
b111 '
#840
b1000 %
b1000 )
b1000 '
#845
b1001 %
b1001 )
b1001 '
#850
0"
1#
b1010 %
b1010 )
b1010 '
#855
1!
0#
b1011 %
b1011 )
b1011 '
#860
b1100 %
b1100 )
b1100 '
#865
b1101 %
b1101 )
b1101 '
#870
b1110 %
b1110 )
b1110 '
#875
b1111 %
b1111 )
b1111 '
#880
0!
1"
b0 %
b0 )
b1011 $
b1011 (
b1011 &
b0 '
#885
b1 %
b1 )
b1 '
#890
b10 %
b10 )
b10 '
#895
b11 %
b11 )
b11 '
#900
b100 %
b100 )
b100 '
#905
b101 %
b101 )
b101 '
#910
b110 %
b110 )
b110 '
#915
b111 %
b111 )
b111 '
#920
b1000 %
b1000 )
b1000 '
#925
b1001 %
b1001 )
b1001 '
#930
b1010 %
b1010 )
b1010 '
#935
0"
1#
b1011 %
b1011 )
b1011 '
#940
1!
0#
b1100 %
b1100 )
b1100 '
#945
b1101 %
b1101 )
b1101 '
#950
b1110 %
b1110 )
b1110 '
#955
b1111 %
b1111 )
b1111 '
#960
0!
1"
b0 %
b0 )
b1100 $
b1100 (
b1100 &
b0 '
#965
b1 %
b1 )
b1 '
#970
b10 %
b10 )
b10 '
#975
b11 %
b11 )
b11 '
#980
b100 %
b100 )
b100 '
#985
b101 %
b101 )
b101 '
#990
b110 %
b110 )
b110 '
#995
b111 %
b111 )
b111 '
#1000
b1000 %
b1000 )
b1000 '
#1005
b1001 %
b1001 )
b1001 '
#1010
b1010 %
b1010 )
b1010 '
#1015
b1011 %
b1011 )
b1011 '
#1020
0"
1#
b1100 %
b1100 )
b1100 '
#1025
1!
0#
b1101 %
b1101 )
b1101 '
#1030
b1110 %
b1110 )
b1110 '
#1035
b1111 %
b1111 )
b1111 '
#1040
0!
1"
b0 %
b0 )
b1101 $
b1101 (
b1101 &
b0 '
#1045
b1 %
b1 )
b1 '
#1050
b10 %
b10 )
b10 '
#1055
b11 %
b11 )
b11 '
#1060
b100 %
b100 )
b100 '
#1065
b101 %
b101 )
b101 '
#1070
b110 %
b110 )
b110 '
#1075
b111 %
b111 )
b111 '
#1080
b1000 %
b1000 )
b1000 '
#1085
b1001 %
b1001 )
b1001 '
#1090
b1010 %
b1010 )
b1010 '
#1095
b1011 %
b1011 )
b1011 '
#1100
b1100 %
b1100 )
b1100 '
#1105
0"
1#
b1101 %
b1101 )
b1101 '
#1110
1!
0#
b1110 %
b1110 )
b1110 '
#1115
b1111 %
b1111 )
b1111 '
#1120
0!
1"
b0 %
b0 )
b1110 $
b1110 (
b1110 &
b0 '
#1125
b1 %
b1 )
b1 '
#1130
b10 %
b10 )
b10 '
#1135
b11 %
b11 )
b11 '
#1140
b100 %
b100 )
b100 '
#1145
b101 %
b101 )
b101 '
#1150
b110 %
b110 )
b110 '
#1155
b111 %
b111 )
b111 '
#1160
b1000 %
b1000 )
b1000 '
#1165
b1001 %
b1001 )
b1001 '
#1170
b1010 %
b1010 )
b1010 '
#1175
b1011 %
b1011 )
b1011 '
#1180
b1100 %
b1100 )
b1100 '
#1185
b1101 %
b1101 )
b1101 '
#1190
0"
1#
b1110 %
b1110 )
b1110 '
#1195
1!
0#
b1111 %
b1111 )
b1111 '
#1200
0!
1"
b0 %
b0 )
b1111 $
b1111 (
b1111 &
b0 '
#1205
b1 %
b1 )
b1 '
#1210
b10 %
b10 )
b10 '
#1215
b11 %
b11 )
b11 '
#1220
b100 %
b100 )
b100 '
#1225
b101 %
b101 )
b101 '
#1230
b110 %
b110 )
b110 '
#1235
b111 %
b111 )
b111 '
#1240
b1000 %
b1000 )
b1000 '
#1245
b1001 %
b1001 )
b1001 '
#1250
b1010 %
b1010 )
b1010 '
#1255
b1011 %
b1011 )
b1011 '
#1260
b1100 %
b1100 )
b1100 '
#1265
b1101 %
b1101 )
b1101 '
#1270
b1110 %
b1110 )
b1110 '
#1275
0"
1#
b1111 %
b1111 )
b1111 '
#1280
b10000 &
b10000 '
