Day19_priority_encoder_casez/priority_encoder_casez.v
module priority_encoder_casez(
    input  [3:0] in,
    output reg [1:0] out, 
    output reg valid 
);

always @(*) begin
    casez (in)               
        4'b1???: begin       
            out = 2'b11;
            valid = 1;
        end
        4'b01??: begin       
            out = 2'b10;
            valid = 1;
        end
        4'b001?: begin       
            out = 2'b01;
            valid = 1;
        end
        4'b0001: begin       
            out = 2'b00;
            valid = 1;
        end
        default: begin      
            out = 2'b00;
            valid = 0;
        end
    endcase
end

endmodule

Day19_priority_encoder_casez/tb_priority_encoder_casez.v
module tb_priority_encoder_casez ;

reg [3:0]tb_in ;
wire [1:0]tb_out ;

priority_encoder_casez dut (
	.in(tb_in),.out(tb_out),.valid(tb_valid)
);

initial begin 

	tb_in = 4'b0000 ; #10
	tb_in = 4'b0001 ; #10
	tb_in = 4'b0010 ; #10
	tb_in = 4'b0011 ; #10
	tb_in = 4'b0100 ; #10
	tb_in = 4'b0101 ; #10
	tb_in = 4'b0110 ; #10
	tb_in = 4'b0111 ; #10
	tb_in = 4'b1000 ; #10
	tb_in = 4'b1001 ; #10
	tb_in = 4'b1010 ; #10
	tb_in = 4'b1011 ; #10
	tb_in = 4'b1100 ; #10
	tb_in = 4'b1101 ; #10
	tb_in = 4'b1110 ; #10
	tb_in = 4'b1111 ; #10
	$finish ;
end

initial begin 

	$dumpfile("tb_priority_encoder_casez.vcd");
	$dumpvars(0,tb_priority_encoder_casez);
end

endmodule

Day19_priority_encoder_casez/tb_priority_encoder_casez.vcd
$date
	Tue Nov 11 04:58:48 2025
$end
$version
	Icarus Verilog
$end
$timescale
	1s
$end
$scope module tb_priority_encoder_casez $end
$var wire 1 ! tb_valid $end
$var wire 2 " tb_out [1:0] $end
$var reg 4 # tb_in [3:0] $end
$scope module dut $end
$var wire 4 $ in [3:0] $end
$var reg 2 % out [1:0] $end
$var reg 1 ! valid $end
$upscope $end
$upscope $end
$enddefinitions $end
#0
$dumpvars
b0 %
b0 $
b0 #
b0 "
0!
$end
#10
1!
b1 #
b1 $
#20
b1 "
b1 %
b10 #
b10 $
#30
b11 #
b11 $
#40
b10 "
b10 %
b100 #
b100 $
#50
b101 #
b101 $
#60
b110 #
b110 $
#70
b111 #
b111 $
#80
b11 "
b11 %
b1000 #
b1000 $
#90
b1001 #
b1001 $
#100
b1010 #
b1010 $
#110
b1011 #
b1011 $
#120
b1100 #
b1100 $
#130
b1101 #
b1101 $
#140
b1110 #
b1110 $
#150
b1111 #
b1111 $
