Day11_decoder3x8/decoder3x8.v
module decoder3x8 (
	input i1_in ,
	input i2_in ,
	input i3_in ,
	output o1_out ,
	output o2_out ,
	output o3_out ,
	output o4_out ,
	output o5_out ,
	output o6_out ,
	output o7_out ,
	output o8_out 
);

assign o1_out = (~i1_in) & (~i2_in) & (~i3_in) ;
assign o2_out = (~i1_in) & (~i2_in) & (i3_in) ;
assign o3_out = (~i1_in) & (i2_in) & (~i3_in) ;
assign o4_out = (~i1_in) & (i2_in) & (i3_in) ;
assign o5_out = (i1_in) & (~i2_in) & (~i3_in) ;
assign o6_out = (i1_in) & (~i2_in) & (i3_in) ;
assign o7_out = (i1_in) & (i2_in) & (~i3_in) ;
assign o8_out = (i1_in) & (i2_in) & (i3_in) ;

endmodule

Day11_decoder3x8/tb_decoder3x8.v
module tb_decoder3x8 ;

reg tb_i1_in ,tb_i2_in ,tb_i3_in ;
output tb_o1_out,tb_o2_out,tb_o3_out,tb_o4_out,tb_o5_out,tb_o6_out,tb_o7_out ,tb_o8_out ;

decoder3x8 dut (
	.i1_in(tb_i1_in),.i2_in(tb_i2_in),.i3_in(tb_i3_in), 
	.o1_out(tb_o1_out),.o2_out(tb_o2_out),.o3_out(tb_o3_out),.o4_out(tb_o4_out),.o5_out(tb_o5_out),.o6_out(tb_o6_out),.o7_out(tb_o7_out),.o8_out(tb_o8_out)
);

initial begin 

	tb_i1_in = 1'b0 ; tb_i2_in = 1'b0 ; tb_i3_in = 1'b0 ;
#10	tb_i1_in = 1'b0 ; tb_i2_in = 1'b0 ; tb_i3_in = 1'b1 ;
#10	tb_i1_in = 1'b0 ; tb_i2_in = 1'b1 ; tb_i3_in = 1'b0 ;
#10	tb_i1_in = 1'b0 ; tb_i2_in = 1'b1 ; tb_i3_in = 1'b1 ;
#10	tb_i1_in = 1'b1 ; tb_i2_in = 1'b0 ; tb_i3_in = 1'b0 ;
#10	tb_i1_in = 1'b1 ; tb_i2_in = 1'b0 ; tb_i3_in = 1'b1 ;
#10	tb_i1_in = 1'b1 ; tb_i2_in = 1'b1 ; tb_i3_in = 1'b0 ;
#10	tb_i1_in = 1'b1 ; tb_i2_in = 1'b1 ; tb_i3_in = 1'b1 ;
#10 $finish ;

end

initial begin 

	$dumpfile("tb_decoder3x8.vcd");
	$dumpvars(0,tb_decoder3x8);
end

endmodule

Day11_decoder3x8/tb_decoder3x8.vcd
$date
	Wed Nov  5 06:52:11 2025
$end
$version
	Icarus Verilog
$end
$timescale
	1s
$end
$scope module tb_decoder3x8 $end
$var wire 1 ! tb_o8_out $end
$var wire 1 " tb_o7_out $end
$var wire 1 # tb_o6_out $end
$var wire 1 $ tb_o5_out $end
$var wire 1 % tb_o4_out $end
$var wire 1 & tb_o3_out $end
$var wire 1 ' tb_o2_out $end
$var wire 1 ( tb_o1_out $end
$var reg 1 ) tb_i1_in $end
$var reg 1 * tb_i2_in $end
$var reg 1 + tb_i3_in $end
$scope module dut $end
$var wire 1 ) i1_in $end
$var wire 1 * i2_in $end
$var wire 1 + i3_in $end
$var wire 1 ( o1_out $end
$var wire 1 ' o2_out $end
$var wire 1 & o3_out $end
$var wire 1 % o4_out $end
$var wire 1 $ o5_out $end
$var wire 1 # o6_out $end
$var wire 1 " o7_out $end
$var wire 1 ! o8_out $end
$upscope $end
$upscope $end
$enddefinitions $end
#0
$dumpvars
0+
0*
0)
1(
0'
0&
0%
0$
0#
0"
0!
$end
#10
0(
1'
1+
#20
1&
0'
0+
1*
#30
0&
1%
1+
#40
1$
0%
0+
0*
1)
#50
0$
1#
1+
#60
1"
0#
0+
1*
#70
0"
1!
1+
