Day13_parity_generator/paritybit_generator.v
module paritybit_generator (
	input a_in ,
	input b_in ,
	input c_in ,
	output paritybit 
);

assign paritybit = a_in ^ b_in ^ c_in ;

endmodule

Day13_parity_generator/tb_paritybit_generator.v
module tb_paritybit_generator ;

reg tb_a_in,tb_b_in,tb_c_in ;
wire tb_paritybit ;

paritybit_generator dut (
	.a_in(tb_a_in),.b_in(tb_b_in),.c_in(tb_c_in),.paritybit(tb_paritybit)
);

initial begin

	tb_a_in = 1'b0 ; tb_b_in = 1'b0 ; tb_c_in = 1'b0 ;
#10	tb_a_in = 1'b0 ; tb_b_in = 1'b0 ; tb_c_in = 1'b1 ;
#10	tb_a_in = 1'b0 ; tb_b_in = 1'b1 ; tb_c_in = 1'b0 ;
#10	tb_a_in = 1'b0 ; tb_b_in = 1'b1 ; tb_c_in = 1'b1 ;
#10	tb_a_in = 1'b1 ; tb_b_in = 1'b0 ; tb_c_in = 1'b0 ;
#10	tb_a_in = 1'b1 ; tb_b_in = 1'b0 ; tb_c_in = 1'b1 ;
#10	tb_a_in = 1'b1 ; tb_b_in = 1'b1 ; tb_c_in = 1'b0 ;
#10	tb_a_in = 1'b1 ; tb_b_in = 1'b1 ; tb_c_in = 1'b1 ;
#10 $finish ;

end

initial begin 

	$dumpfile("tb_paritybit_generator.vcd");
	$dumpvars(0,tb_paritybit_generator);
end

endmodule

Day13_parity_generator/tb_paritybit_generator.vcd
$date
	Wed Nov  5 08:47:40 2025
$end
$version
	Icarus Verilog
$end
$timescale
	1s
$end
$scope module tb_paritybit_generator $end
$var wire 1 ! tb_paritybit $end
$var reg 1 " tb_a_in $end
$var reg 1 # tb_b_in $end
$var reg 1 $ tb_c_in $end
$scope module dut $end
$var wire 1 " a_in $end
$var wire 1 # b_in $end
$var wire 1 $ c_in $end
$var wire 1 ! paritybit $end
$upscope $end
$upscope $end
$enddefinitions $end
#0
$dumpvars
0$
0#
0"
0!
$end
#10
1!
1$
#20
0$
1#
#30
0!
1$
#40
1!
0$
0#
1"
#50
0!
1$
#60
0$
1#
#70
1!
1$
