Day15_basicALU/basicALU.v
module basicALU (
    input  [3:0] a_in,
    input  [3:0] b_in,
    input  [2:0] sel,
    output [4:0] y_out
);

wire [4:0] sum_out, sub_out, incA_out, decA_out;
wire [4:0] and_out, or_out, xor_out, notA_out;

assign sum_out  = a_in + b_in;
assign sub_out  = a_in - b_in;
assign incA_out = a_in + 1;
assign decA_out = a_in - 1;

assign and_out  = {1'b0, (a_in & b_in)};
assign or_out   = {1'b0, (a_in | b_in)};
assign xor_out  = {1'b0, (a_in ^ b_in)};
assign notA_out = {1'b0, (~a_in)};

assign y_out =
       (sel == 3'b000) ? sum_out  :
       (sel == 3'b001) ? sub_out  :
       (sel == 3'b010) ? incA_out :
       (sel == 3'b011) ? decA_out :
       (sel == 3'b100) ? and_out  :
       (sel == 3'b101) ? or_out   :
       (sel == 3'b110) ? xor_out  :
                         notA_out ;

endmodule

Day15_basicALU/tb_basicALU.v
module tb_basicALU ;

reg[3:0] tb_a_in ;
reg[3:0] tb_b_in ;
reg [2:0] tb_sel ;
wire [4:0] tb_y_out ;
integer i,j,k ;

basicALU dut (
	.a_in(tb_a_in),.b_in(tb_b_in),.sel(tb_sel),.y_out(tb_y_out)
);

initial begin 
	
	for(i = 0; i < 16 ;i= i + 1)begin
		for(j =0 ; j < 16 ;j= j + 1)begin
			for(k = 0 ; k < 8 ;k= k + 1)begin
				tb_a_in = i;
			        tb_b_in = j;
				tb_sel = k;
				#10;
			end
		end
	end
	$finish ;
end

initial begin 

	$dumpfile("tb_basicALU.vcd");
	$dumpvars(0,tb_basicALU);
end

endmodule

Day15_basicALU/tb_basicALU.vcd
$date
	Thu Nov  6 05:19:55 2025
$end
$version
	Icarus Verilog
$end
$timescale
	1s
$end
$scope module tb_basicALU $end
$var wire 5 ! tb_y_out [4:0] $end
$var reg 4 " tb_a_in [3:0] $end
$var reg 4 # tb_b_in [3:0] $end
$var reg 3 $ tb_sel [2:0] $end
$var integer 32 % i [31:0] $end
$var integer 32 & j [31:0] $end
$var integer 32 ' k [31:0] $end
$scope module dut $end
$var wire 4 ( a_in [3:0] $end
$var wire 4 ) b_in [3:0] $end
$var wire 3 * sel [2:0] $end
$var wire 5 + y_out [4:0] $end
$var wire 5 , xor_out [4:0] $end
$var wire 5 - sum_out [4:0] $end
$var wire 5 . sub_out [4:0] $end
$var wire 5 / or_out [4:0] $end
$var wire 5 0 notA_out [4:0] $end
$var wire 5 1 incA_out [4:0] $end
$var wire 5 2 decA_out [4:0] $end
$var wire 5 3 and_out [4:0] $end
$upscope $end
$upscope $end
$enddefinitions $end
#0
$dumpvars
b0 3
b11111 2
b1 1
b1111 0
b0 /
b0 .
b0 -
b0 ,
b0 +
b0 *
b0 )
b0 (
b0 '
b0 &
b0 %
b0 $
b0 #
b0 "
b0 !
$end
#10
b1 $
b1 *
b1 '
#20
b1 !
b1 +
b10 $
b10 *
b10 '
#30
b11111 !
b11111 +
b11 $
b11 *
b11 '
#40
b0 !
b0 +
b100 $
b100 *
b100 '
#50
b101 $
b101 *
b101 '
#60
b110 $
b110 *
b110 '
#70
b1111 !
b1111 +
b111 $
b111 *
b111 '
#80
b1 !
b1 +
b1 /
b1 ,
b0 $
b0 *
b1 -
b11111 .
b1 #
b1 )
b1 &
b0 '
#90
b11111 !
b11111 +
b1 $
b1 *
b1 '
#100
b1 !
b1 +
b10 $
b10 *
b10 '
#110
b11111 !
b11111 +
b11 $
b11 *
b11 '
#120
b0 !
b0 +
b100 $
b100 *
b100 '
#130
b1 !
b1 +
b101 $
b101 *
b101 '
#140
b110 $
b110 *
b110 '
#150
b1111 !
b1111 +
b111 $
b111 *
b111 '
#160
b10 !
b10 +
b10 /
b10 ,
b0 $
b0 *
b10 -
b11110 .
b10 #
b10 )
b10 &
b0 '
#170
b11110 !
b11110 +
b1 $
b1 *
b1 '
#180
b1 !
b1 +
b10 $
b10 *
b10 '
#190
b11111 !
b11111 +
b11 $
b11 *
b11 '
#200
b0 !
b0 +
b100 $
b100 *
b100 '
#210
b10 !
b10 +
b101 $
b101 *
b101 '
#220
b110 $
b110 *
b110 '
#230
b1111 !
b1111 +
b111 $
b111 *
b111 '
#240
b11 !
b11 +
b11 /
b11 ,
b0 $
b0 *
b11 -
b11101 .
b11 #
b11 )
b11 &
b0 '
#250
b11101 !
b11101 +
b1 $
b1 *
b1 '
#260
b1 !
b1 +
b10 $
b10 *
b10 '
#270
b11111 !
b11111 +
b11 $
b11 *
b11 '
#280
b0 !
b0 +
b100 $
b100 *
b100 '
#290
b11 !
b11 +
b101 $
b101 *
b101 '
#300
b110 $
b110 *
b110 '
#310
b1111 !
b1111 +
b111 $
b111 *
b111 '
#320
b100 !
b100 +
b100 /
b100 ,
b0 $
b0 *
b100 -
b11100 .
b100 #
b100 )
b100 &
b0 '
#330
b11100 !
b11100 +
b1 $
b1 *
b1 '
#340
b1 !
b1 +
b10 $
b10 *
b10 '
#350
b11111 !
b11111 +
b11 $
b11 *
b11 '
#360
b0 !
b0 +
b100 $
b100 *
b100 '
#370
b100 !
b100 +
b101 $
b101 *
b101 '
#380
b110 $
b110 *
b110 '
#390
b1111 !
b1111 +
b111 $
b111 *
b111 '
#400
b101 !
b101 +
b101 /
b101 ,
b0 $
b0 *
b101 -
b11011 .
b101 #
b101 )
b101 &
b0 '
#410
b11011 !
b11011 +
b1 $
b1 *
b1 '
#420
b1 !
b1 +
b10 $
b10 *
b10 '
#430
b11111 !
b11111 +
b11 $
b11 *
b11 '
#440
b0 !
b0 +
b100 $
b100 *
b100 '
#450
b101 !
b101 +
b101 $
b101 *
b101 '
#460
b110 $
b110 *
b110 '
#470
b1111 !
b1111 +
b111 $
b111 *
b111 '
#480
b110 !
b110 +
b110 /
b110 ,
b0 $
b0 *
b110 -
b11010 .
b110 #
b110 )
b110 &
b0 '
#490
b11010 !
b11010 +
b1 $
b1 *
b1 '
#500
b1 !
b1 +
b10 $
b10 *
b10 '
#510
b11111 !
b11111 +
b11 $
b11 *
b11 '
#520
b0 !
b0 +
b100 $
b100 *
b100 '
#530
b110 !
b110 +
b101 $
b101 *
b101 '
#540
b110 $
b110 *
b110 '
#550
b1111 !
b1111 +
b111 $
b111 *
b111 '
#560
b111 !
b111 +
b111 /
b111 ,
b0 $
b0 *
b111 -
b11001 .
b111 #
b111 )
b111 &
b0 '
#570
b11001 !
b11001 +
b1 $
b1 *
b1 '
#580
b1 !
b1 +
b10 $
b10 *
b10 '
#590
b11111 !
b11111 +
b11 $
b11 *
b11 '
#600
b0 !
b0 +
b100 $
b100 *
b100 '
#610
b111 !
b111 +
b101 $
b101 *
b101 '
#620
b110 $
b110 *
b110 '
#630
b1111 !
b1111 +
b111 $
b111 *
b111 '
#640
b1000 !
b1000 +
b1000 /
b1000 ,
b0 $
b0 *
b1000 -
b11000 .
b1000 #
b1000 )
b1000 &
b0 '
#650
b11000 !
b11000 +
b1 $
b1 *
b1 '
#660
b1 !
b1 +
b10 $
b10 *
b10 '
#670
b11111 !
b11111 +
b11 $
b11 *
b11 '
#680
b0 !
b0 +
b100 $
b100 *
b100 '
#690
b1000 !
b1000 +
b101 $
b101 *
b101 '
#700
b110 $
b110 *
b110 '
#710
b1111 !
b1111 +
b111 $
b111 *
b111 '
#720
b1001 !
b1001 +
b1001 /
b1001 ,
b0 $
b0 *
b1001 -
b10111 .
b1001 #
b1001 )
b1001 &
b0 '
#730
b10111 !
b10111 +
b1 $
b1 *
b1 '
#740
b1 !
b1 +
b10 $
b10 *
b10 '
#750
b11111 !
b11111 +
b11 $
b11 *
b11 '
#760
b0 !
b0 +
b100 $
b100 *
b100 '
#770
b1001 !
b1001 +
b101 $
b101 *
b101 '
#780
b110 $
b110 *
b110 '
#790
b1111 !
b1111 +
b111 $
b111 *
b111 '
#800
b1010 !
b1010 +
b1010 /
b1010 ,
b0 $
b0 *
b1010 -
b10110 .
b1010 #
b1010 )
b1010 &
b0 '
#810
b10110 !
b10110 +
b1 $
b1 *
b1 '
#820
b1 !
b1 +
b10 $
b10 *
b10 '
#830
b11111 !
b11111 +
b11 $
b11 *
b11 '
#840
b0 !
b0 +
b100 $
b100 *
b100 '
#850
b1010 !
b1010 +
b101 $
b101 *
b101 '
#860
b110 $
b110 *
b110 '
#870
b1111 !
b1111 +
b111 $
b111 *
b111 '
#880
b1011 !
b1011 +
b1011 /
b1011 ,
b0 $
b0 *
b1011 -
b10101 .
b1011 #
b1011 )
b1011 &
b0 '
#890
b10101 !
b10101 +
b1 $
b1 *
b1 '
#900
b1 !
b1 +
b10 $
b10 *
b10 '
#910
b11111 !
b11111 +
b11 $
b11 *
b11 '
#920
b0 !
b0 +
b100 $
b100 *
b100 '
#930
b1011 !
b1011 +
b101 $
b101 *
b101 '
#940
b110 $
b110 *
b110 '
#950
b1111 !
b1111 +
b111 $
b111 *
b111 '
#960
b1100 !
b1100 +
b1100 /
b1100 ,
b0 $
b0 *
b1100 -
b10100 .
b1100 #
b1100 )
b1100 &
b0 '
#970
b10100 !
b10100 +
b1 $
b1 *
b1 '
#980
b1 !
b1 +
b10 $
b10 *
b10 '
#990
b11111 !
b11111 +
b11 $
b11 *
b11 '
#1000
b0 !
b0 +
b100 $
b100 *
b100 '
#1010
b1100 !
b1100 +
b101 $
b101 *
b101 '
#1020
b110 $
b110 *
b110 '
#1030
b1111 !
b1111 +
b111 $
b111 *
b111 '
#1040
b1101 !
b1101 +
b1101 /
b1101 ,
b0 $
b0 *
b1101 -
b10011 .
b1101 #
b1101 )
b1101 &
b0 '
#1050
b10011 !
b10011 +
b1 $
b1 *
b1 '
#1060
b1 !
b1 +
b10 $
b10 *
b10 '
#1070
b11111 !
b11111 +
b11 $
b11 *
b11 '
#1080
b0 !
b0 +
b100 $
b100 *
b100 '
#1090
b1101 !
b1101 +
b101 $
b101 *
b101 '
#1100
b110 $
b110 *
b110 '
#1110
b1111 !
b1111 +
b111 $
b111 *
b111 '
#1120
b1110 !
b1110 +
b1110 /
b1110 ,
b0 $
b0 *
b1110 -
b10010 .
b1110 #
b1110 )
b1110 &
b0 '
#1130
b10010 !
b10010 +
b1 $
b1 *
b1 '
#1140
b1 !
b1 +
b10 $
b10 *
b10 '
#1150
b11111 !
b11111 +
b11 $
b11 *
b11 '
#1160
b0 !
b0 +
b100 $
b100 *
b100 '
#1170
b1110 !
b1110 +
b101 $
b101 *
b101 '
#1180
b110 $
b110 *
b110 '
#1190
b1111 !
b1111 +
b111 $
b111 *
b111 '
#1200
b1111 /
b1111 ,
b0 $
b0 *
b1111 -
b10001 .
b1111 #
b1111 )
b1111 &
b0 '
#1210
b10001 !
b10001 +
b1 $
b1 *
b1 '
#1220
b1 !
b1 +
b10 $
b10 *
b10 '
#1230
b11111 !
b11111 +
b11 $
b11 *
b11 '
#1240
b0 !
b0 +
b100 $
b100 *
b100 '
#1250
b1111 !
b1111 +
b101 $
b101 *
b101 '
#1260
b110 $
b110 *
b110 '
#1270
b111 $
b111 *
b111 '
#1280
b1 !
b1 +
b1 /
b1 ,
b1110 0
b0 $
b0 *
b0 #
b0 )
b1 -
b1 .
b10 1
b0 2
b1 "
b1 (
b1 %
b0 &
b0 '
#1290
b1 $
b1 *
b1 '
#1300
b10 !
b10 +
b10 $
b10 *
b10 '
#1310
b0 !
b0 +
b11 $
b11 *
b11 '
#1320
b100 $
b100 *
b100 '
#1330
b1 !
b1 +
b101 $
b101 *
b101 '
#1340
b110 $
b110 *
b110 '
#1350
b1110 !
b1110 +
b111 $
b111 *
b111 '
#1360
b10 !
b10 +
b1 3
b0 ,
b0 $
b0 *
b10 -
b0 .
b1 #
b1 )
b1 &
b0 '
#1370
b0 !
b0 +
b1 $
b1 *
b1 '
#1380
b10 !
b10 +
b10 $
b10 *
b10 '
#1390
b0 !
b0 +
b11 $
b11 *
b11 '
#1400
b1 !
b1 +
b100 $
b100 *
b100 '
#1410
b101 $
b101 *
b101 '
#1420
b0 !
b0 +
b110 $
b110 *
b110 '
#1430
b1110 !
b1110 +
b111 $
b111 *
b111 '
#1440
b11 !
b11 +
b0 3
b11 /
b11 ,
b0 $
b0 *
b11 -
b11111 .
b10 #
b10 )
b10 &
b0 '
#1450
b11111 !
b11111 +
b1 $
b1 *
b1 '
#1460
b10 !
b10 +
b10 $
b10 *
b10 '
#1470
b0 !
b0 +
b11 $
b11 *
b11 '
#1480
b100 $
b100 *
b100 '
#1490
b11 !
b11 +
b101 $
b101 *
b101 '
#1500
b110 $
b110 *
b110 '
#1510
b1110 !
b1110 +
b111 $
b111 *
b111 '
#1520
b100 !
b100 +
b1 3
b10 ,
b0 $
b0 *
b100 -
b11110 .
b11 #
b11 )
b11 &
b0 '
#1530
b11110 !
b11110 +
b1 $
b1 *
b1 '
#1540
b10 !
b10 +
b10 $
b10 *
b10 '
#1550
b0 !
b0 +
b11 $
b11 *
b11 '
#1560
b1 !
b1 +
b100 $
b100 *
b100 '
#1570
b11 !
b11 +
b101 $
b101 *
b101 '
#1580
b10 !
b10 +
b110 $
b110 *
b110 '
#1590
b1110 !
b1110 +
b111 $
b111 *
b111 '
#1600
b101 !
b101 +
b0 3
b101 /
b101 ,
b0 $
b0 *
b101 -
b11101 .
b100 #
b100 )
b100 &
b0 '
#1610
b11101 !
b11101 +
b1 $
b1 *
b1 '
#1620
b10 !
b10 +
b10 $
b10 *
b10 '
#1630
b0 !
b0 +
b11 $
b11 *
b11 '
#1640
b100 $
b100 *
b100 '
#1650
b101 !
b101 +
b101 $
b101 *
b101 '
#1660
b110 $
b110 *
b110 '
#1670
b1110 !
b1110 +
b111 $
b111 *
b111 '
#1680
b110 !
b110 +
b1 3
b100 ,
b0 $
b0 *
b110 -
b11100 .
b101 #
b101 )
b101 &
b0 '
#1690
b11100 !
b11100 +
b1 $
b1 *
b1 '
#1700
b10 !
b10 +
b10 $
b10 *
b10 '
#1710
b0 !
b0 +
b11 $
b11 *
b11 '
#1720
b1 !
b1 +
b100 $
b100 *
b100 '
#1730
b101 !
b101 +
b101 $
b101 *
b101 '
#1740
b100 !
b100 +
b110 $
b110 *
b110 '
#1750
b1110 !
b1110 +
b111 $
b111 *
b111 '
#1760
b111 !
b111 +
b0 3
b111 /
b111 ,
b0 $
b0 *
b111 -
b11011 .
b110 #
b110 )
b110 &
b0 '
#1770
b11011 !
b11011 +
b1 $
b1 *
b1 '
#1780
b10 !
b10 +
b10 $
b10 *
b10 '
#1790
b0 !
b0 +
b11 $
b11 *
b11 '
#1800
b100 $
b100 *
b100 '
#1810
b111 !
b111 +
b101 $
b101 *
b101 '
#1820
b110 $
b110 *
b110 '
#1830
b1110 !
b1110 +
b111 $
b111 *
b111 '
#1840
b1000 !
b1000 +
b1 3
b110 ,
b0 $
b0 *
b1000 -
b11010 .
b111 #
b111 )
b111 &
b0 '
#1850
b11010 !
b11010 +
b1 $
b1 *
b1 '
#1860
b10 !
b10 +
b10 $
b10 *
b10 '
#1870
b0 !
b0 +
b11 $
b11 *
b11 '
#1880
b1 !
b1 +
b100 $
b100 *
b100 '
#1890
b111 !
b111 +
b101 $
b101 *
b101 '
#1900
b110 !
b110 +
b110 $
b110 *
b110 '
#1910
b1110 !
b1110 +
b111 $
b111 *
b111 '
#1920
b1001 !
b1001 +
b0 3
b1001 /
b1001 ,
b0 $
b0 *
b1001 -
b11001 .
b1000 #
b1000 )
b1000 &
b0 '
#1930
b11001 !
b11001 +
b1 $
b1 *
b1 '
#1940
b10 !
b10 +
b10 $
b10 *
b10 '
#1950
b0 !
b0 +
b11 $
b11 *
b11 '
#1960
b100 $
b100 *
b100 '
#1970
b1001 !
b1001 +
b101 $
b101 *
b101 '
#1980
b110 $
b110 *
b110 '
#1990
b1110 !
b1110 +
b111 $
b111 *
b111 '
#2000
b1010 !
b1010 +
b1 3
b1000 ,
b0 $
b0 *
b1010 -
b11000 .
b1001 #
b1001 )
b1001 &
b0 '
#2010
b11000 !
b11000 +
b1 $
b1 *
b1 '
#2020
b10 !
b10 +
b10 $
b10 *
b10 '
#2030
b0 !
b0 +
b11 $
b11 *
b11 '
#2040
b1 !
b1 +
b100 $
b100 *
b100 '
#2050
b1001 !
b1001 +
b101 $
b101 *
b101 '
#2060
b1000 !
b1000 +
b110 $
b110 *
b110 '
#2070
b1110 !
b1110 +
b111 $
b111 *
b111 '
#2080
b1011 !
b1011 +
b0 3
b1011 /
b1011 ,
b0 $
b0 *
b1011 -
b10111 .
b1010 #
b1010 )
b1010 &
b0 '
#2090
b10111 !
b10111 +
b1 $
b1 *
b1 '
#2100
b10 !
b10 +
b10 $
b10 *
b10 '
#2110
b0 !
b0 +
b11 $
b11 *
b11 '
#2120
b100 $
b100 *
b100 '
#2130
b1011 !
b1011 +
b101 $
b101 *
b101 '
#2140
b110 $
b110 *
b110 '
#2150
b1110 !
b1110 +
b111 $
b111 *
b111 '
#2160
b1100 !
b1100 +
b1 3
b1010 ,
b0 $
b0 *
b1100 -
b10110 .
b1011 #
b1011 )
b1011 &
b0 '
#2170
b10110 !
b10110 +
b1 $
b1 *
b1 '
#2180
b10 !
b10 +
b10 $
b10 *
b10 '
#2190
b0 !
b0 +
b11 $
b11 *
b11 '
#2200
b1 !
b1 +
b100 $
b100 *
b100 '
#2210
b1011 !
b1011 +
b101 $
b101 *
b101 '
#2220
b1010 !
b1010 +
b110 $
b110 *
b110 '
#2230
b1110 !
b1110 +
b111 $
b111 *
b111 '
#2240
b1101 !
b1101 +
b0 3
b1101 /
b1101 ,
b0 $
b0 *
b1101 -
b10101 .
b1100 #
b1100 )
b1100 &
b0 '
#2250
b10101 !
b10101 +
b1 $
b1 *
b1 '
#2260
b10 !
b10 +
b10 $
b10 *
b10 '
#2270
b0 !
b0 +
b11 $
b11 *
b11 '
#2280
b100 $
b100 *
b100 '
#2290
b1101 !
b1101 +
b101 $
b101 *
b101 '
#2300
b110 $
b110 *
b110 '
#2310
b1110 !
b1110 +
b111 $
b111 *
b111 '
#2320
b1 3
b1100 ,
b0 $
b0 *
b1110 -
b10100 .
b1101 #
b1101 )
b1101 &
b0 '
#2330
b10100 !
b10100 +
b1 $
b1 *
b1 '
#2340
b10 !
b10 +
b10 $
b10 *
b10 '
#2350
b0 !
b0 +
b11 $
b11 *
b11 '
#2360
b1 !
b1 +
b100 $
b100 *
b100 '
#2370
b1101 !
b1101 +
b101 $
b101 *
b101 '
#2380
b1100 !
b1100 +
b110 $
b110 *
b110 '
#2390
b1110 !
b1110 +
b111 $
b111 *
b111 '
#2400
b1111 !
b1111 +
b0 3
b1111 /
b1111 ,
b0 $
b0 *
b1111 -
b10011 .
b1110 #
b1110 )
b1110 &
b0 '
#2410
b10011 !
b10011 +
b1 $
b1 *
b1 '
#2420
b10 !
b10 +
b10 $
b10 *
b10 '
#2430
b0 !
b0 +
b11 $
b11 *
b11 '
#2440
b100 $
b100 *
b100 '
#2450
b1111 !
b1111 +
b101 $
b101 *
b101 '
#2460
b110 $
b110 *
b110 '
#2470
b1110 !
b1110 +
b111 $
b111 *
b111 '
#2480
b10000 !
b10000 +
b1 3
b1110 ,
b0 $
b0 *
b10000 -
b10010 .
b1111 #
b1111 )
b1111 &
b0 '
#2490
b10010 !
b10010 +
b1 $
b1 *
b1 '
#2500
b10 !
b10 +
b10 $
b10 *
b10 '
#2510
b0 !
b0 +
b11 $
b11 *
b11 '
#2520
b1 !
b1 +
b100 $
b100 *
b100 '
#2530
b1111 !
b1111 +
b101 $
b101 *
b101 '
#2540
b1110 !
b1110 +
b110 $
b110 *
b110 '
#2550
b111 $
b111 *
b111 '
#2560
b10 !
b10 +
b0 3
b10 /
b10 ,
b1101 0
b0 $
b0 *
b0 #
b0 )
b10 -
b10 .
b11 1
b1 2
b10 "
b10 (
b10 %
b0 &
b0 '
#2570
b1 $
b1 *
b1 '
#2580
b11 !
b11 +
b10 $
b10 *
b10 '
#2590
b1 !
b1 +
b11 $
b11 *
b11 '
#2600
b0 !
b0 +
b100 $
b100 *
b100 '
#2610
b10 !
b10 +
b101 $
b101 *
b101 '
#2620
b110 $
b110 *
b110 '
#2630
b1101 !
b1101 +
b111 $
b111 *
b111 '
#2640
b11 !
b11 +
b11 /
b11 ,
b0 $
b0 *
b11 -
b1 .
b1 #
b1 )
b1 &
b0 '
#2650
b1 !
b1 +
b1 $
b1 *
b1 '
#2660
b11 !
b11 +
b10 $
b10 *
b10 '
#2670
b1 !
b1 +
b11 $
b11 *
b11 '
#2680
b0 !
b0 +
b100 $
b100 *
b100 '
#2690
b11 !
b11 +
b101 $
b101 *
b101 '
#2700
b110 $
b110 *
b110 '
#2710
b1101 !
b1101 +
b111 $
b111 *
b111 '
#2720
b100 !
b100 +
b10 3
b10 /
b0 ,
b0 $
b0 *
b100 -
b0 .
b10 #
b10 )
b10 &
b0 '
#2730
b0 !
b0 +
b1 $
b1 *
b1 '
#2740
b11 !
b11 +
b10 $
b10 *
b10 '
#2750
b1 !
b1 +
b11 $
b11 *
b11 '
#2760
b10 !
b10 +
b100 $
b100 *
b100 '
#2770
b101 $
b101 *
b101 '
#2780
b0 !
b0 +
b110 $
b110 *
b110 '
#2790
b1101 !
b1101 +
b111 $
b111 *
b111 '
#2800
b101 !
b101 +
b11 /
b1 ,
b0 $
b0 *
b101 -
b11111 .
b11 #
b11 )
b11 &
b0 '
#2810
b11111 !
b11111 +
b1 $
b1 *
b1 '
#2820
b11 !
b11 +
b10 $
b10 *
b10 '
#2830
b1 !
b1 +
b11 $
b11 *
b11 '
#2840
b10 !
b10 +
b100 $
b100 *
b100 '
#2850
b11 !
b11 +
b101 $
b101 *
b101 '
#2860
b1 !
b1 +
b110 $
b110 *
b110 '
#2870
b1101 !
b1101 +
b111 $
b111 *
b111 '
#2880
b110 !
b110 +
b0 3
b110 /
b110 ,
b0 $
b0 *
b110 -
b11110 .
b100 #
b100 )
b100 &
b0 '
#2890
b11110 !
b11110 +
b1 $
b1 *
b1 '
#2900
b11 !
b11 +
b10 $
b10 *
b10 '
#2910
b1 !
b1 +
b11 $
b11 *
b11 '
#2920
b0 !
b0 +
b100 $
b100 *
b100 '
#2930
b110 !
b110 +
b101 $
b101 *
b101 '
#2940
b110 $
b110 *
b110 '
#2950
b1101 !
b1101 +
b111 $
b111 *
b111 '
#2960
b111 !
b111 +
b111 /
b111 ,
b0 $
b0 *
b111 -
b11101 .
b101 #
b101 )
b101 &
b0 '
#2970
b11101 !
b11101 +
b1 $
b1 *
b1 '
#2980
b11 !
b11 +
b10 $
b10 *
b10 '
#2990
b1 !
b1 +
b11 $
b11 *
b11 '
#3000
b0 !
b0 +
b100 $
b100 *
b100 '
#3010
b111 !
b111 +
b101 $
b101 *
b101 '
#3020
b110 $
b110 *
b110 '
#3030
b1101 !
b1101 +
b111 $
b111 *
b111 '
#3040
b1000 !
b1000 +
b10 3
b110 /
b100 ,
b0 $
b0 *
b1000 -
b11100 .
b110 #
b110 )
b110 &
b0 '
#3050
b11100 !
b11100 +
b1 $
b1 *
b1 '
#3060
b11 !
b11 +
b10 $
b10 *
b10 '
#3070
b1 !
b1 +
b11 $
b11 *
b11 '
#3080
b10 !
b10 +
b100 $
b100 *
b100 '
#3090
b110 !
b110 +
b101 $
b101 *
b101 '
#3100
b100 !
b100 +
b110 $
b110 *
b110 '
#3110
b1101 !
b1101 +
b111 $
b111 *
b111 '
#3120
b1001 !
b1001 +
b111 /
b101 ,
b0 $
b0 *
b1001 -
b11011 .
b111 #
b111 )
b111 &
b0 '
#3130
b11011 !
b11011 +
b1 $
b1 *
b1 '
#3140
b11 !
b11 +
b10 $
b10 *
b10 '
#3150
b1 !
b1 +
b11 $
b11 *
b11 '
#3160
b10 !
b10 +
b100 $
b100 *
b100 '
#3170
b111 !
b111 +
b101 $
b101 *
b101 '
#3180
b101 !
b101 +
b110 $
b110 *
b110 '
#3190
b1101 !
b1101 +
b111 $
b111 *
b111 '
#3200
b1010 !
b1010 +
b0 3
b1010 /
b1010 ,
b0 $
b0 *
b1010 -
b11010 .
b1000 #
b1000 )
b1000 &
b0 '
#3210
b11010 !
b11010 +
b1 $
b1 *
b1 '
#3220
b11 !
b11 +
b10 $
b10 *
b10 '
#3230
b1 !
b1 +
b11 $
b11 *
b11 '
#3240
b0 !
b0 +
b100 $
b100 *
b100 '
#3250
b1010 !
b1010 +
b101 $
b101 *
b101 '
#3260
b110 $
b110 *
b110 '
#3270
b1101 !
b1101 +
b111 $
b111 *
b111 '
#3280
b1011 !
b1011 +
b1011 /
b1011 ,
b0 $
b0 *
b1011 -
b11001 .
b1001 #
b1001 )
b1001 &
b0 '
#3290
b11001 !
b11001 +
b1 $
b1 *
b1 '
#3300
b11 !
b11 +
b10 $
b10 *
b10 '
#3310
b1 !
b1 +
b11 $
b11 *
b11 '
#3320
b0 !
b0 +
b100 $
b100 *
b100 '
#3330
b1011 !
b1011 +
b101 $
b101 *
b101 '
#3340
b110 $
b110 *
b110 '
#3350
b1101 !
b1101 +
b111 $
b111 *
b111 '
#3360
b1100 !
b1100 +
b10 3
b1010 /
b1000 ,
b0 $
b0 *
b1100 -
b11000 .
b1010 #
b1010 )
b1010 &
b0 '
#3370
b11000 !
b11000 +
b1 $
b1 *
b1 '
#3380
b11 !
b11 +
b10 $
b10 *
b10 '
#3390
b1 !
b1 +
b11 $
b11 *
b11 '
#3400
b10 !
b10 +
b100 $
b100 *
b100 '
#3410
b1010 !
b1010 +
b101 $
b101 *
b101 '
#3420
b1000 !
b1000 +
b110 $
b110 *
b110 '
#3430
b1101 !
b1101 +
b111 $
b111 *
b111 '
#3440
b1011 /
b1001 ,
b0 $
b0 *
b1101 -
b10111 .
b1011 #
b1011 )
b1011 &
b0 '
#3450
b10111 !
b10111 +
b1 $
b1 *
b1 '
#3460
b11 !
b11 +
b10 $
b10 *
b10 '
#3470
b1 !
b1 +
b11 $
b11 *
b11 '
#3480
b10 !
b10 +
b100 $
b100 *
b100 '
#3490
b1011 !
b1011 +
b101 $
b101 *
b101 '
#3500
b1001 !
b1001 +
b110 $
b110 *
b110 '
#3510
b1101 !
b1101 +
b111 $
b111 *
b111 '
#3520
b1110 !
b1110 +
b0 3
b1110 /
b1110 ,
b0 $
b0 *
b1110 -
b10110 .
b1100 #
b1100 )
b1100 &
b0 '
#3530
b10110 !
b10110 +
b1 $
b1 *
b1 '
#3540
b11 !
b11 +
b10 $
b10 *
b10 '
#3550
b1 !
b1 +
b11 $
b11 *
b11 '
#3560
b0 !
b0 +
b100 $
b100 *
b100 '
#3570
b1110 !
b1110 +
b101 $
b101 *
b101 '
#3580
b110 $
b110 *
b110 '
#3590
b1101 !
b1101 +
b111 $
b111 *
b111 '
#3600
b1111 !
b1111 +
b1111 /
b1111 ,
b0 $
b0 *
b1111 -
b10101 .
b1101 #
b1101 )
b1101 &
b0 '
#3610
b10101 !
b10101 +
b1 $
b1 *
b1 '
#3620
b11 !
b11 +
b10 $
b10 *
b10 '
#3630
b1 !
b1 +
b11 $
b11 *
b11 '
#3640
b0 !
b0 +
b100 $
b100 *
b100 '
#3650
b1111 !
b1111 +
b101 $
b101 *
b101 '
#3660
b110 $
b110 *
b110 '
#3670
b1101 !
b1101 +
b111 $
b111 *
b111 '
#3680
b10000 !
b10000 +
b10 3
b1110 /
b1100 ,
b0 $
b0 *
b10000 -
b10100 .
b1110 #
b1110 )
b1110 &
b0 '
#3690
b10100 !
b10100 +
b1 $
b1 *
b1 '
#3700
b11 !
b11 +
b10 $
b10 *
b10 '
#3710
b1 !
b1 +
b11 $
b11 *
b11 '
#3720
b10 !
b10 +
b100 $
b100 *
b100 '
#3730
b1110 !
b1110 +
b101 $
b101 *
b101 '
#3740
b1100 !
b1100 +
b110 $
b110 *
b110 '
#3750
b1101 !
b1101 +
b111 $
b111 *
b111 '
#3760
b10001 !
b10001 +
b1111 /
b1101 ,
b0 $
b0 *
b10001 -
b10011 .
b1111 #
b1111 )
b1111 &
b0 '
#3770
b10011 !
b10011 +
b1 $
b1 *
b1 '
#3780
b11 !
b11 +
b10 $
b10 *
b10 '
#3790
b1 !
b1 +
b11 $
b11 *
b11 '
#3800
b10 !
b10 +
b100 $
b100 *
b100 '
#3810
b1111 !
b1111 +
b101 $
b101 *
b101 '
#3820
b1101 !
b1101 +
b110 $
b110 *
b110 '
#3830
b111 $
b111 *
b111 '
#3840
b11 !
b11 +
b0 3
b11 /
b11 ,
b1100 0
b0 $
b0 *
b0 #
b0 )
b11 -
b11 .
b100 1
b10 2
b11 "
b11 (
b11 %
b0 &
b0 '
#3850
b1 $
b1 *
b1 '
#3860
b100 !
b100 +
b10 $
b10 *
b10 '
#3870
b10 !
b10 +
b11 $
b11 *
b11 '
#3880
b0 !
b0 +
b100 $
b100 *
b100 '
#3890
b11 !
b11 +
b101 $
b101 *
b101 '
#3900
b110 $
b110 *
b110 '
#3910
b1100 !
b1100 +
b111 $
b111 *
b111 '
#3920
b100 !
b100 +
b1 3
b10 ,
b0 $
b0 *
b100 -
b10 .
b1 #
b1 )
b1 &
b0 '
#3930
b10 !
b10 +
b1 $
b1 *
b1 '
#3940
b100 !
b100 +
b10 $
b10 *
b10 '
#3950
b10 !
b10 +
b11 $
b11 *
b11 '
#3960
b1 !
b1 +
b100 $
b100 *
b100 '
#3970
b11 !
b11 +
b101 $
b101 *
b101 '
#3980
b10 !
b10 +
b110 $
b110 *
b110 '
#3990
b1100 !
b1100 +
b111 $
b111 *
b111 '
#4000
b101 !
b101 +
b10 3
b1 ,
b0 $
b0 *
b101 -
b1 .
b10 #
b10 )
b10 &
b0 '
#4010
b1 !
b1 +
b1 $
b1 *
b1 '
#4020
b100 !
b100 +
b10 $
b10 *
b10 '
#4030
b10 !
b10 +
b11 $
b11 *
b11 '
#4040
b100 $
b100 *
b100 '
#4050
b11 !
b11 +
b101 $
b101 *
b101 '
