Day05_full_sub/full_sub.v
module full_sub (d_out,b_out,a2_out,a3_out,a1_out,n_out,a_in,b_in,c_in);

input a_in,b_in,c_in;
output d_out,b_out;
inout a1_out,a2_out,a3_out,n_out;

xor dut1 (d_out,a_in,b_in,c_in);
not dut6 (n_out,a_in);
and dut2 (a1_out,n_out,b_in);
and dut3 (a2_out,n_out,c_in);
and dut4 (a3_out,b_in,c_in);
or dut5 (b_out,a1_out,a2_out,a3_out);

endmodule

Day05_full_sub/tb_full_sub.v
module tb_full_sub;

reg tb_a_in,tb_b_in,tb_c_in;
wire tb_d_out,tb_b_out;
inout tb_a1_out,tb_a2_out,tb_a3_out,tb_n_out;

full_sub dut (.d_out(tb_d_out),.b_out(tb_b_out),.a1_out(tb_a1_out),.a2_out(tb_a2_out),.a3_out(tb_a3_out),.n_out(tb_n_out),.a_in(tb_a_in),.b_in(tb_b_in),.c_in(tb_c_in));

initial begin

	tb_a_in = 1'b0 ; tb_b_in = 1'b0 ; tb_c_in = 1'b0 ;
#10	tb_a_in = 1'b0 ; tb_b_in = 1'b0 ; tb_c_in = 1'b1 ;
#10	tb_a_in = 1'b0 ; tb_b_in = 1'b1 ; tb_c_in = 1'b0 ;
#10	tb_a_in = 1'b0 ; tb_b_in = 1'b1 ; tb_c_in = 1'b1 ;
#10	tb_a_in = 1'b1 ; tb_b_in = 1'b0 ; tb_c_in = 1'b0 ;
#10	tb_a_in = 1'b1 ; tb_b_in = 1'b0 ; tb_c_in = 1'b1 ;
#10	tb_a_in = 1'b1 ; tb_b_in = 1'b1 ; tb_c_in = 1'b0 ;
#10	tb_a_in = 1'b1 ; tb_b_in = 1'b1 ; tb_c_in = 1'b1 ;
#10     $finish;

end

initial begin 

	$dumpfile("tb_full_sub.vcd");
	$dumpvars(0,tb_full_sub);

end

endmodule

Day05_full_sub/tb_full_sub.vcd
$date
	Sat Aug  9 08:57:57 2025
$end
$version
	Icarus Verilog
$end
$timescale
	1s
$end
$scope module tb_full_sub $end
$var wire 1 ! tb_n_out $end
$var wire 1 " tb_d_out $end
$var wire 1 # tb_b_out $end
$var wire 1 $ tb_a3_out $end
$var wire 1 % tb_a2_out $end
$var wire 1 & tb_a1_out $end
$var reg 1 ' tb_a_in $end
$var reg 1 ( tb_b_in $end
$var reg 1 ) tb_c_in $end
$scope module dut $end
$var wire 1 & a1_out $end
$var wire 1 % a2_out $end
$var wire 1 $ a3_out $end
$var wire 1 ' a_in $end
$var wire 1 ( b_in $end
$var wire 1 # b_out $end
$var wire 1 ) c_in $end
$var wire 1 " d_out $end
$var wire 1 ! n_out $end
$upscope $end
$upscope $end
$enddefinitions $end
#0
$dumpvars
0)
0(
0'
0&
0%
0$
0#
0"
1!
$end
#10
1#
1"
1%
1)
#20
0%
1&
0)
1(
#30
0"
1%
1$
1)
#40
0#
0%
0&
0$
1"
0!
0)
0(
1'
#50
0"
1)
#60
0)
1(
#70
1#
1"
1$
1)
