Day10_encoder8x3/encoder8x3.v
module encoder8x3 (
	input i0_in , input i1_in , input i2_in , input i3_in , input i4_in , input i5_in , input i6_in , input i7_in ,
        output o1_out, output o2_out , output o3_out 
);

assign o1_out = i0_in | i3_in | i4_in | i5_in ;
assign o2_out = i1_in | i3_in | i4_in | i6_in ;
assign o3_out = i2_in | i4_in | i5_in | i6_in ;

endmodule

Day10_encoder8x3/tb_encoder8x3.v
module tb_encoder8x3 ;

reg tb_i0_in ,tb_i1_in ,tb_i2_in ,tb_i3_in ,tb_i4_in ,tb_i5_in ,tb_i6_in ,tb_i7_in ;
wire tb_o1_out , tb_o2_out , tb_o3_out ;

encoder8x3 dut (

	.i0_in(tb_i0_in) ,.i1_in(tb_i1_in) ,.i2_in(tb_i2_in) ,.i3_in(tb_i3_in) ,.i4_in(tb_i4_in) ,.i5_in(tb_i5_in) ,.i6_in(tb_i6_in) ,.i7_in(tb_i7_in),
        .o1_out(tb_o1_out) , .o2_out(tb_o2_out) , .o3_out(tb_o3_out)
);

initial begin 

	tb_i0_in = 1'b1 ;tb_i1_in = 1'b0 ;tb_i2_in = 1'b0 ;tb_i3_in = 1'b0 ;tb_i4_in = 1'b0 ;tb_i5_in = 1'b0 ;tb_i6_in = 1'b0 ;tb_i7_in = 1'b0 ;
#10	tb_i0_in = 1'b0 ;tb_i1_in = 1'b1 ;tb_i2_in = 1'b0 ;tb_i3_in = 1'b0 ;tb_i4_in = 1'b0 ;tb_i5_in = 1'b0 ;tb_i6_in = 1'b0 ;tb_i7_in = 1'b0 ;
#10	tb_i0_in = 1'b0 ;tb_i1_in = 1'b0 ;tb_i2_in = 1'b1 ;tb_i3_in = 1'b0 ;tb_i4_in = 1'b0 ;tb_i5_in = 1'b0 ;tb_i6_in = 1'b0 ;tb_i7_in = 1'b0 ;
#10	tb_i0_in = 1'b0 ;tb_i1_in = 1'b0 ;tb_i2_in = 1'b0 ;tb_i3_in = 1'b1 ;tb_i4_in = 1'b0 ;tb_i5_in = 1'b0 ;tb_i6_in = 1'b0 ;tb_i7_in = 1'b0 ;
#10	tb_i0_in = 1'b0 ;tb_i1_in = 1'b0 ;tb_i2_in = 1'b0 ;tb_i3_in = 1'b0 ;tb_i4_in = 1'b1 ;tb_i5_in = 1'b0 ;tb_i6_in = 1'b0 ;tb_i7_in = 1'b0 ;
#10	tb_i0_in = 1'b0 ;tb_i1_in = 1'b0 ;tb_i2_in = 1'b0 ;tb_i3_in = 1'b0 ;tb_i4_in = 1'b0 ;tb_i5_in = 1'b1 ;tb_i6_in = 1'b0 ;tb_i7_in = 1'b0 ;
#10	tb_i0_in = 1'b0 ;tb_i1_in = 1'b0 ;tb_i2_in = 1'b0 ;tb_i3_in = 1'b0 ;tb_i4_in = 1'b0 ;tb_i5_in = 1'b0 ;tb_i6_in = 1'b1 ;tb_i7_in = 1'b0 ;
#10	tb_i0_in = 1'b0 ;tb_i1_in = 1'b0 ;tb_i2_in = 1'b0 ;tb_i3_in = 1'b0 ;tb_i4_in = 1'b0 ;tb_i5_in = 1'b0 ;tb_i6_in = 1'b0 ;tb_i7_in = 1'b1 ;
#10 $finish ;

end

initial begin 

	$monitor("time=%0t tb_i0_in = %b tb_i1_in = %b tb_i2_in = %b tb_i3_in = %b ;tb_i4_in = %b tb_i5_in = %b tb_i6_in = %b tb_i7_in = %b | tb_o1_out = %b tb_o2_out = %b tb_o3_out = %b ",$time,tb_i0_in,tb_i1_in,tb_i2_in,tb_i3_in,tb_i4_in,tb_i5_in,tb_i6_in,tb_i7_in,tb_o1_out,tb_o2_out,tb_o3_out) ;

end

initial begin 

	$dumpfile("tb_encoder8x3.vcd");
	$dumpvars(0,tb_encoder8x3);
end 

endmodule

Day10_encoder8x3/tb_encoder8x3.vcd
$date
	Tue Nov  4 08:28:55 2025
$end
$version
	Icarus Verilog
$end
$timescale
	1s
$end
$scope module tb_encoder8x3 $end
$var wire 1 ! tb_o3_out $end
$var wire 1 " tb_o2_out $end
$var wire 1 # tb_o1_out $end
$var reg 1 $ tb_i0_in $end
$var reg 1 % tb_i1_in $end
$var reg 1 & tb_i2_in $end
$var reg 1 ' tb_i3_in $end
$var reg 1 ( tb_i4_in $end
$var reg 1 ) tb_i5_in $end
$var reg 1 * tb_i6_in $end
$var reg 1 + tb_i7_in $end
$scope module dut $end
$var wire 1 $ i0_in $end
$var wire 1 % i1_in $end
$var wire 1 & i2_in $end
$var wire 1 ' i3_in $end
$var wire 1 ( i4_in $end
$var wire 1 ) i5_in $end
$var wire 1 * i6_in $end
$var wire 1 + i7_in $end
$var wire 1 # o1_out $end
$var wire 1 " o2_out $end
$var wire 1 ! o3_out $end
$upscope $end
$upscope $end
$enddefinitions $end
#0
$dumpvars
0+
0*
0)
0(
0'
0&
0%
1$
1#
0"
0!
$end
#10
1"
0#
1%
0$
#20
1!
0"
1&
0%
#30
1#
1"
0!
1'
0&
#40
1!
1(
0'
#50
0"
1)
0(
#60
1"
0#
1*
0)
#70
0"
0!
1+
0*
