Day21_alu_beh/fbit_alu_beh.v
module fbit_alu_beh (
    input  [3:0] a_in,
    input  [3:0] b_in,
    input  [3:0] sel,
    output reg [4:0] out,
    output reg c_out, b_out,
    output reg c_flag, b_flag
);

    reg [4:0] temp;

    always @(*) begin

        out     = 5'b00000;
        c_out   = 1'b0;
        b_out   = 1'b0;
        c_flag  = 1'b0;
        b_flag  = 1'b0;

        case(sel)
            4'b0000: begin
                temp   = a_in + b_in;
                {c_out, out} = temp;
                c_flag = c_out;
            end

            4'b0001: begin
                temp = a_in - b_in;
                b_out = (a_in < b_in);
                out   = temp[3:0];
                b_flag = b_out;
            end

            4'b0010: begin
                temp = b_in - a_in;
                b_out = (b_in < a_in);
                out   = temp[3:0];
                b_flag = b_out;
            end

            4'b0011: begin
                temp = a_in + 1;
                {c_out, out} = temp;
                c_flag = c_out;
            end

            4'b0100: begin
                temp = a_in - 1;
                b_out = (a_in < 1);
                out   = temp[3:0];
                b_flag = b_out;
            end

            4'b0101: out = a_in & b_in;
            4'b0110: out = a_in | b_in;     
            4'b0111: out = a_in ^ b_in;        

            4'b1000: out = ~a_in;           
            4'b1001: out = {a_in[2:0], a_in[3]}; 
            4'b1010: out = {a_in[0], a_in[3:1]}; 

            4'b1011: out = a_in << 1;           
            4'b1100: out = a_in >> 1;          

            4'b1101: out = (a_in > b_in) ? 5'b00001 : 5'b00000; 
            4'b1110: out = (a_in == b_in) ? 5'b00001 : 5'b00000;

            4'b1111: out = 5'b00000;
        endcase
    end

endmodule

Day21_alu_beh/tb_fbit_alu_beh.v
module tb_fbit_alu_beh ;

reg  [3:0] tb_a_in ;
reg  [3:0] tb_b_in ;
reg  [3:0] tb_sel ;
wire [4:0] tb_out ;
wire tb_c_out, tb_b_out, tb_c_flag, tb_b_flag ;

integer i,j,k;

fbit_alu_beh dut (
    .a_in(tb_a_in),
    .b_in(tb_b_in),
    .sel(tb_sel),
    .out(tb_out),
    .c_out(tb_c_out),
    .b_out(tb_b_out),
    .c_flag(tb_c_flag),
    .b_flag(tb_b_flag)
);

initial begin
    for(i=0;i<16;i=i+1)begin
        for(j=0;j<16;j=j+1)begin
            for(k=0;k<16;k=k+1)begin
                tb_a_in = i ;
                tb_b_in = j ;
                tb_sel = k ;
                #5;
            end
        end
    end
    $finish ;
end

initial begin 
    $dumpfile("tb_fbit_alu_beh.vcd");
    $dumpvars(0,tb_fbit_alu_beh);
end

initial begin
    $monitor("t=%0t | A=%b B=%b SEL=%b | OUT=%b | C=%b B=%b CF=%b BF=%b",
              $time, tb_a_in, tb_b_in, tb_sel, tb_out,
              tb_c_out, tb_b_out, tb_c_flag, tb_b_flag);
end

endmodule

Day21_alu_beh/tb_fbit_alu_beh.vcd
$date
	Tue Nov 11 08:23:31 2025
$end
$version
	Icarus Verilog
$end
$timescale
	1s
$end
$scope module tb_fbit_alu_beh $end
$var wire 5 ! tb_out [4:0] $end
$var wire 1 " tb_c_out $end
$var wire 1 # tb_c_flag $end
$var wire 1 $ tb_b_out $end
$var wire 1 % tb_b_flag $end
$var reg 4 & tb_a_in [3:0] $end
$var reg 4 ' tb_b_in [3:0] $end
$var reg 4 ( tb_sel [3:0] $end
$var integer 32 ) i [31:0] $end
$var integer 32 * j [31:0] $end
$var integer 32 + k [31:0] $end
$scope module dut $end
$var wire 4 , a_in [3:0] $end
$var wire 4 - b_in [3:0] $end
$var wire 4 . sel [3:0] $end
$var reg 1 % b_flag $end
$var reg 1 $ b_out $end
$var reg 1 # c_flag $end
$var reg 1 " c_out $end
$var reg 5 / out [4:0] $end
$var reg 5 0 temp [4:0] $end
$upscope $end
$upscope $end
$enddefinitions $end
#0
$dumpvars
b0 0
b0 /
b0 .
b0 -
b0 ,
b0 +
b0 *
b0 )
b0 (
b0 '
b0 &
0%
0$
0#
0"
b0 !
$end
#5
b1 (
b1 .
b1 +
#10
b10 (
b10 .
b10 +
#15
b1 !
b1 /
b1 0
b11 (
b11 .
b11 +
#20
1%
1$
b11111 0
b1111 !
b1111 /
b100 (
b100 .
b100 +
#25
0%
0$
b0 !
b0 /
b101 (
b101 .
b101 +
#30
b110 (
b110 .
b110 +
#35
b111 (
b111 .
b111 +
#40
b11111 !
b11111 /
b1000 (
b1000 .
b1000 +
#45
b0 !
b0 /
b1001 (
b1001 .
b1001 +
#50
b1010 (
b1010 .
b1010 +
#55
b1011 (
b1011 .
b1011 +
#60
b1100 (
b1100 .
b1100 +
#65
b1101 (
b1101 .
b1101 +
#70
b1 !
b1 /
b1110 (
b1110 .
b1110 +
#75
b0 !
b0 /
b1111 (
b1111 .
b1111 +
#80
b1 !
b1 /
b1 0
b0 (
b0 .
b1 '
b1 -
b1 *
b0 +
#85
1%
1$
b11111 0
b1111 !
b1111 /
b1 (
b1 .
b1 +
#90
b1 0
0%
0$
b1 !
b1 /
b10 (
b10 .
b10 +
#95
b1 !
b1 /
b11 (
b11 .
b11 +
#100
1%
1$
b11111 0
b1111 !
b1111 /
b100 (
b100 .
b100 +
#105
0%
0$
b0 !
b0 /
b101 (
b101 .
b101 +
#110
b1 !
b1 /
b110 (
b110 .
b110 +
#115
b1 !
b1 /
b111 (
b111 .
b111 +
#120
b11111 !
b11111 /
b1000 (
b1000 .
b1000 +
#125
b0 !
b0 /
b1001 (
b1001 .
b1001 +
#130
b1010 (
b1010 .
b1010 +
#135
b1011 (
b1011 .
b1011 +
#140
b1100 (
b1100 .
b1100 +
#145
b1101 (
b1101 .
b1101 +
#150
b1110 (
b1110 .
b1110 +
#155
b1111 (
b1111 .
b1111 +
#160
b10 !
b10 /
b10 0
b0 (
b0 .
b10 '
b10 -
b10 *
b0 +
#165
1%
1$
b11110 0
b1110 !
b1110 /
b1 (
b1 .
b1 +
#170
b10 0
0%
0$
b10 !
b10 /
b10 (
b10 .
b10 +
#175
b1 0
b1 !
b1 /
b11 (
b11 .
b11 +
#180
1%
1$
b11111 0
b1111 !
b1111 /
b100 (
b100 .
b100 +
#185
0%
0$
b0 !
b0 /
b101 (
b101 .
b101 +
#190
b10 !
b10 /
b110 (
b110 .
b110 +
#195
b10 !
b10 /
b111 (
b111 .
b111 +
#200
b11111 !
b11111 /
b1000 (
b1000 .
b1000 +
#205
b0 !
b0 /
b1001 (
b1001 .
b1001 +
#210
b1010 (
b1010 .
b1010 +
#215
b1011 (
b1011 .
b1011 +
#220
b1100 (
b1100 .
b1100 +
#225
b1101 (
b1101 .
b1101 +
#230
b1110 (
b1110 .
b1110 +
#235
b1111 (
b1111 .
b1111 +
#240
b11 !
b11 /
b11 0
b0 (
b0 .
b11 '
b11 -
b11 *
b0 +
#245
1%
1$
b11101 0
b1101 !
b1101 /
b1 (
b1 .
b1 +
#250
b11 0
0%
0$
b11 !
b11 /
b10 (
b10 .
b10 +
#255
b1 0
b1 !
b1 /
b11 (
b11 .
b11 +
#260
1%
1$
b11111 0
b1111 !
b1111 /
b100 (
b100 .
b100 +
#265
0%
0$
b0 !
b0 /
b101 (
b101 .
b101 +
#270
b11 !
b11 /
b110 (
b110 .
b110 +
#275
b11 !
b11 /
b111 (
b111 .
b111 +
#280
b11111 !
b11111 /
b1000 (
b1000 .
b1000 +
#285
b0 !
b0 /
b1001 (
b1001 .
b1001 +
#290
b1010 (
b1010 .
b1010 +
#295
b1011 (
b1011 .
b1011 +
#300
b1100 (
b1100 .
b1100 +
#305
b1101 (
b1101 .
b1101 +
#310
b1110 (
b1110 .
b1110 +
#315
b1111 (
b1111 .
b1111 +
#320
b100 !
b100 /
b100 0
b0 (
b0 .
b100 '
b100 -
b100 *
b0 +
#325
1%
1$
b11100 0
b1100 !
b1100 /
b1 (
b1 .
b1 +
#330
b100 0
0%
0$
b100 !
b100 /
b10 (
b10 .
b10 +
#335
b1 0
b1 !
b1 /
b11 (
b11 .
b11 +
#340
1%
1$
b11111 0
b1111 !
b1111 /
b100 (
b100 .
b100 +
#345
0%
0$
b0 !
b0 /
b101 (
b101 .
b101 +
#350
b100 !
b100 /
b110 (
b110 .
b110 +
#355
b100 !
b100 /
b111 (
b111 .
b111 +
#360
b11111 !
b11111 /
b1000 (
b1000 .
b1000 +
#365
b0 !
b0 /
b1001 (
b1001 .
b1001 +
#370
b1010 (
b1010 .
b1010 +
#375
b1011 (
b1011 .
b1011 +
#380
b1100 (
b1100 .
b1100 +
#385
b1101 (
b1101 .
b1101 +
#390
b1110 (
b1110 .
b1110 +
#395
b1111 (
b1111 .
b1111 +
#400
b101 !
b101 /
b101 0
b0 (
b0 .
b101 '
b101 -
b101 *
b0 +
#405
1%
1$
b11011 0
b1011 !
b1011 /
b1 (
b1 .
b1 +
#410
b101 0
0%
0$
b101 !
b101 /
b10 (
b10 .
b10 +
#415
b1 0
b1 !
b1 /
b11 (
b11 .
b11 +
#420
1%
1$
b11111 0
b1111 !
b1111 /
b100 (
b100 .
b100 +
#425
0%
0$
b0 !
b0 /
b101 (
b101 .
b101 +
#430
b101 !
b101 /
b110 (
b110 .
b110 +
#435
b101 !
b101 /
b111 (
b111 .
b111 +
#440
b11111 !
b11111 /
b1000 (
b1000 .
b1000 +
#445
b0 !
b0 /
b1001 (
b1001 .
b1001 +
#450
b1010 (
b1010 .
b1010 +
#455
b1011 (
b1011 .
b1011 +
#460
b1100 (
b1100 .
b1100 +
#465
b1101 (
b1101 .
b1101 +
#470
b1110 (
b1110 .
b1110 +
#475
b1111 (
b1111 .
b1111 +
#480
b110 !
b110 /
b110 0
b0 (
b0 .
b110 '
b110 -
b110 *
b0 +
#485
1%
1$
b11010 0
b1010 !
b1010 /
b1 (
b1 .
b1 +
#490
b110 0
0%
0$
b110 !
b110 /
b10 (
b10 .
b10 +
#495
b1 0
b1 !
b1 /
b11 (
b11 .
b11 +
#500
1%
1$
b11111 0
b1111 !
b1111 /
b100 (
b100 .
b100 +
#505
0%
0$
b0 !
b0 /
b101 (
b101 .
b101 +
#510
b110 !
b110 /
b110 (
b110 .
b110 +
#515
b110 !
b110 /
b111 (
b111 .
b111 +
#520
b11111 !
b11111 /
b1000 (
b1000 .
b1000 +
#525
b0 !
b0 /
b1001 (
b1001 .
b1001 +
#530
b1010 (
b1010 .
b1010 +
#535
b1011 (
b1011 .
b1011 +
#540
b1100 (
b1100 .
b1100 +
#545
b1101 (
b1101 .
b1101 +
#550
b1110 (
b1110 .
b1110 +
#555
b1111 (
b1111 .
b1111 +
#560
b111 !
b111 /
b111 0
b0 (
b0 .
b111 '
b111 -
b111 *
b0 +
#565
1%
1$
b11001 0
b1001 !
b1001 /
b1 (
b1 .
b1 +
#570
b111 0
0%
0$
b111 !
b111 /
b10 (
b10 .
b10 +
#575
b1 0
b1 !
b1 /
b11 (
b11 .
b11 +
#580
1%
1$
b11111 0
b1111 !
b1111 /
b100 (
b100 .
b100 +
#585
0%
0$
b0 !
b0 /
b101 (
b101 .
b101 +
#590
b111 !
b111 /
b110 (
b110 .
b110 +
#595
b111 !
b111 /
b111 (
b111 .
b111 +
#600
b11111 !
b11111 /
b1000 (
b1000 .
b1000 +
#605
b0 !
b0 /
b1001 (
b1001 .
b1001 +
#610
b1010 (
b1010 .
b1010 +
#615
b1011 (
b1011 .
b1011 +
#620
b1100 (
b1100 .
b1100 +
#625
b1101 (
b1101 .
b1101 +
#630
b1110 (
b1110 .
b1110 +
#635
b1111 (
b1111 .
b1111 +
#640
b1000 !
b1000 /
b1000 0
b0 (
b0 .
b1000 '
b1000 -
b1000 *
b0 +
#645
1%
1$
b11000 0
b1000 !
b1000 /
b1 (
b1 .
b1 +
#650
b1000 0
0%
0$
b1000 !
b1000 /
b10 (
b10 .
b10 +
#655
b1 0
b1 !
b1 /
b11 (
b11 .
b11 +
#660
1%
1$
b11111 0
b1111 !
b1111 /
b100 (
b100 .
b100 +
#665
0%
0$
b0 !
b0 /
b101 (
b101 .
b101 +
#670
b1000 !
b1000 /
b110 (
b110 .
b110 +
#675
b1000 !
b1000 /
b111 (
b111 .
b111 +
#680
b11111 !
b11111 /
b1000 (
b1000 .
b1000 +
#685
b0 !
b0 /
b1001 (
b1001 .
b1001 +
#690
b1010 (
b1010 .
b1010 +
#695
b1011 (
b1011 .
b1011 +
#700
b1100 (
b1100 .
b1100 +
#705
b1101 (
b1101 .
b1101 +
#710
b1110 (
b1110 .
b1110 +
#715
b1111 (
b1111 .
b1111 +
#720
b1001 !
b1001 /
b1001 0
b0 (
b0 .
b1001 '
b1001 -
b1001 *
b0 +
#725
1%
1$
b10111 0
b111 !
b111 /
b1 (
b1 .
b1 +
#730
b1001 0
0%
0$
b1001 !
b1001 /
b10 (
b10 .
b10 +
#735
b1 0
b1 !
b1 /
b11 (
b11 .
b11 +
#740
1%
1$
b11111 0
b1111 !
b1111 /
b100 (
b100 .
b100 +
#745
0%
0$
b0 !
b0 /
b101 (
b101 .
b101 +
#750
b1001 !
b1001 /
b110 (
b110 .
b110 +
#755
b1001 !
b1001 /
b111 (
b111 .
b111 +
#760
b11111 !
b11111 /
b1000 (
b1000 .
b1000 +
#765
b0 !
b0 /
b1001 (
b1001 .
b1001 +
#770
b1010 (
b1010 .
b1010 +
#775
b1011 (
b1011 .
b1011 +
#780
b1100 (
b1100 .
b1100 +
#785
b1101 (
b1101 .
b1101 +
#790
b1110 (
b1110 .
b1110 +
#795
b1111 (
b1111 .
b1111 +
#800
b1010 !
b1010 /
b1010 0
b0 (
b0 .
b1010 '
b1010 -
b1010 *
b0 +
#805
1%
1$
b10110 0
b110 !
b110 /
b1 (
b1 .
b1 +
#810
b1010 0
0%
0$
b1010 !
b1010 /
b10 (
b10 .
b10 +
#815
b1 0
b1 !
b1 /
b11 (
b11 .
b11 +
#820
1%
1$
b11111 0
b1111 !
b1111 /
b100 (
b100 .
b100 +
#825
0%
0$
b0 !
b0 /
b101 (
b101 .
b101 +
#830
b1010 !
b1010 /
b110 (
b110 .
b110 +
#835
b1010 !
b1010 /
b111 (
b111 .
b111 +
#840
b11111 !
b11111 /
b1000 (
b1000 .
b1000 +
#845
b0 !
b0 /
b1001 (
b1001 .
b1001 +
#850
b1010 (
b1010 .
b1010 +
#855
b1011 (
b1011 .
b1011 +
#860
b1100 (
b1100 .
b1100 +
#865
b1101 (
b1101 .
b1101 +
#870
b1110 (
b1110 .
b1110 +
#875
b1111 (
b1111 .
b1111 +
#880
b1011 !
b1011 /
b1011 0
b0 (
b0 .
b1011 '
b1011 -
b1011 *
b0 +
#885
1%
1$
b10101 0
b101 !
b101 /
b1 (
b1 .
b1 +
#890
b1011 0
0%
0$
b1011 !
b1011 /
b10 (
b10 .
b10 +
#895
b1 0
b1 !
b1 /
b11 (
b11 .
b11 +
#900
1%
1$
b11111 0
b1111 !
b1111 /
b100 (
b100 .
b100 +
#905
0%
0$
b0 !
b0 /
b101 (
b101 .
b101 +
#910
b1011 !
b1011 /
b110 (
b110 .
b110 +
#915
b1011 !
b1011 /
b111 (
b111 .
b111 +
#920
b11111 !
b11111 /
b1000 (
b1000 .
b1000 +
#925
b0 !
b0 /
b1001 (
b1001 .
b1001 +
#930
b1010 (
b1010 .
b1010 +
#935
b1011 (
b1011 .
b1011 +
#940
b1100 (
b1100 .
b1100 +
#945
b1101 (
b1101 .
b1101 +
#950
b1110 (
b1110 .
b1110 +
#955
b1111 (
b1111 .
b1111 +
#960
b1100 !
b1100 /
b1100 0
b0 (
b0 .
b1100 '
b1100 -
b1100 *
b0 +
#965
1%
1$
b10100 0
b100 !
b100 /
b1 (
b1 .
b1 +
#970
b1100 0
0%
0$
b1100 !
b1100 /
b10 (
b10 .
b10 +
#975
b1 0
b1 !
b1 /
b11 (
b11 .
b11 +
#980
1%
1$
b11111 0
b1111 !
b1111 /
b100 (
b100 .
b100 +
#985
0%
0$
b0 !
b0 /
b101 (
b101 .
b101 +
#990
b1100 !
b1100 /
b110 (
b110 .
b110 +
#995
b1100 !
b1100 /
b111 (
b111 .
b111 +
#1000
b11111 !
b11111 /
b1000 (
b1000 .
b1000 +
#1005
b0 !
b0 /
b1001 (
b1001 .
b1001 +
#1010
b1010 (
b1010 .
b1010 +
#1015
b1011 (
b1011 .
b1011 +
#1020
b1100 (
b1100 .
b1100 +
#1025
b1101 (
b1101 .
b1101 +
#1030
b1110 (
b1110 .
b1110 +
#1035
b1111 (
b1111 .
b1111 +
#1040
b1101 !
b1101 /
b1101 0
b0 (
b0 .
b1101 '
b1101 -
b1101 *
b0 +
#1045
1%
1$
b10011 0
b11 !
b11 /
b1 (
b1 .
b1 +
#1050
b1101 0
0%
0$
b1101 !
b1101 /
b10 (
b10 .
b10 +
#1055
b1 0
b1 !
b1 /
b11 (
b11 .
b11 +
#1060
1%
1$
b11111 0
b1111 !
b1111 /
b100 (
b100 .
b100 +
#1065
0%
0$
b0 !
b0 /
b101 (
b101 .
b101 +
#1070
b1101 !
b1101 /
b110 (
b110 .
b110 +
#1075
b1101 !
b1101 /
b111 (
b111 .
b111 +
#1080
b11111 !
b11111 /
b1000 (
b1000 .
b1000 +
#1085
b0 !
b0 /
b1001 (
b1001 .
b1001 +
#1090
b1010 (
b1010 .
b1010 +
#1095
b1011 (
b1011 .
b1011 +
#1100
b1100 (
b1100 .
b1100 +
#1105
b1101 (
b1101 .
b1101 +
#1110
b1110 (
b1110 .
b1110 +
#1115
b1111 (
b1111 .
b1111 +
#1120
b1110 !
b1110 /
b1110 0
b0 (
b0 .
b1110 '
b1110 -
b1110 *
b0 +
#1125
1%
1$
b10010 0
b10 !
b10 /
b1 (
b1 .
b1 +
#1130
b1110 0
0%
0$
b1110 !
b1110 /
b10 (
b10 .
b10 +
#1135
b1 0
b1 !
b1 /
b11 (
b11 .
b11 +
#1140
1%
1$
b11111 0
b1111 !
b1111 /
b100 (
b100 .
b100 +
#1145
0%
0$
b0 !
b0 /
b101 (
b101 .
b101 +
#1150
b1110 !
b1110 /
b110 (
b110 .
b110 +
#1155
b1110 !
b1110 /
b111 (
b111 .
b111 +
#1160
b11111 !
b11111 /
b1000 (
b1000 .
b1000 +
#1165
b0 !
b0 /
b1001 (
b1001 .
b1001 +
#1170
b1010 (
b1010 .
b1010 +
#1175
b1011 (
b1011 .
b1011 +
#1180
b1100 (
b1100 .
b1100 +
#1185
b1101 (
b1101 .
b1101 +
#1190
b1110 (
b1110 .
b1110 +
#1195
b1111 (
b1111 .
b1111 +
#1200
b1111 !
b1111 /
b1111 0
b0 (
b0 .
b1111 '
b1111 -
b1111 *
b0 +
#1205
1%
1$
b10001 0
b1 !
b1 /
b1 (
b1 .
b1 +
#1210
b1111 0
0%
0$
b1111 !
b1111 /
b10 (
b10 .
b10 +
#1215
b1 0
b1 !
b1 /
b11 (
b11 .
b11 +
#1220
1%
1$
b11111 0
b1111 !
b1111 /
b100 (
b100 .
b100 +
#1225
0%
0$
b0 !
b0 /
b101 (
b101 .
b101 +
#1230
b1111 !
b1111 /
b110 (
b110 .
b110 +
#1235
b1111 !
b1111 /
b111 (
b111 .
b111 +
#1240
b11111 !
b11111 /
b1000 (
b1000 .
b1000 +
#1245
b0 !
b0 /
b1001 (
b1001 .
b1001 +
#1250
b1010 (
b1010 .
b1010 +
#1255
b1011 (
b1011 .
b1011 +
#1260
b1100 (
b1100 .
b1100 +
#1265
b1101 (
b1101 .
b1101 +
#1270
b1110 (
b1110 .
b1110 +
#1275
b1111 (
b1111 .
b1111 +
#1280
b1 !
b1 /
b1 0
b0 (
b0 .
b0 '
b0 -
b1 &
b1 ,
b1 )
b0 *
b0 +
#1285
b1 !
b1 /
b1 (
b1 .
b1 +
#1290
1%
1$
b11111 0
b1111 !
b1111 /
b10 (
b10 .
b10 +
#1295
b10 0
0%
0$
b10 !
b10 /
b11 (
b11 .
b11 +
#1300
b0 0
b0 !
b0 /
b100 (
b100 .
b100 +
#1305
b101 (
b101 .
b101 +
#1310
b1 !
b1 /
b110 (
b110 .
b110 +
#1315
b1 !
b1 /
b111 (
b111 .
b111 +
#1320
b11110 !
b11110 /
b1000 (
b1000 .
b1000 +
#1325
b10 !
b10 /
b1001 (
b1001 .
b1001 +
#1330
b1000 !
b1000 /
b1010 (
b1010 .
b1010 +
#1335
b10 !
b10 /
b1011 (
b1011 .
b1011 +
#1340
b0 !
b0 /
b1100 (
b1100 .
b1100 +
#1345
b1 !
b1 /
b1101 (
b1101 .
b1101 +
#1350
b0 !
b0 /
b1110 (
b1110 .
b1110 +
#1355
b1111 (
b1111 .
b1111 +
#1360
b10 !
b10 /
b10 0
b0 (
b0 .
b1 '
b1 -
b1 *
b0 +
#1365
b0 0
b0 !
b0 /
b1 (
b1 .
b1 +
#1370
b10 (
b10 .
b10 +
#1375
b10 !
b10 /
b10 0
b11 (
b11 .
b11 +
#1380
b0 0
b0 !
b0 /
b100 (
b100 .
b100 +
#1385
b1 !
b1 /
b101 (
b101 .
b101 +
#1390
b1 !
b1 /
b110 (
b110 .
b110 +
#1395
b0 !
b0 /
b111 (
b111 .
b111 +
#1400
b11110 !
b11110 /
b1000 (
b1000 .
b1000 +
#1405
b10 !
b10 /
b1001 (
b1001 .
b1001 +
#1410
b1000 !
b1000 /
b1010 (
b1010 .
b1010 +
#1415
b10 !
b10 /
b1011 (
b1011 .
b1011 +
#1420
b0 !
b0 /
b1100 (
b1100 .
b1100 +
#1425
b1101 (
b1101 .
b1101 +
#1430
b1 !
b1 /
b1110 (
b1110 .
b1110 +
#1435
b0 !
b0 /
b1111 (
b1111 .
b1111 +
#1440
b11 !
b11 /
b11 0
b0 (
b0 .
b10 '
b10 -
b10 *
b0 +
#1445
1%
1$
b11111 0
b1111 !
b1111 /
b1 (
b1 .
b1 +
#1450
b1 0
0%
0$
b1 !
b1 /
b10 (
b10 .
b10 +
#1455
b10 0
b10 !
b10 /
b11 (
b11 .
b11 +
#1460
b0 0
b0 !
b0 /
b100 (
b100 .
b100 +
#1465
b101 (
b101 .
b101 +
#1470
b11 !
b11 /
b110 (
b110 .
b110 +
#1475
b11 !
b11 /
b111 (
b111 .
b111 +
#1480
b11110 !
b11110 /
b1000 (
b1000 .
b1000 +
#1485
b10 !
b10 /
b1001 (
b1001 .
b1001 +
#1490
b1000 !
b1000 /
b1010 (
b1010 .
b1010 +
#1495
b10 !
b10 /
b1011 (
b1011 .
b1011 +
#1500
b0 !
b0 /
b1100 (
b1100 .
b1100 +
#1505
b1101 (
b1101 .
b1101 +
#1510
b1110 (
b1110 .
b1110 +
#1515
b1111 (
b1111 .
b1111 +
#1520
b100 !
b100 /
b100 0
b0 (
b0 .
b11 '
b11 -
b11 *
b0 +
#1525
1%
1$
b11110 0
b1110 !
b1110 /
b1 (
b1 .
b1 +
#1530
b10 0
0%
0$
b10 !
b10 /
b10 (
b10 .
b10 +
#1535
b10 !
b10 /
b11 (
b11 .
b11 +
#1540
b0 0
b0 !
b0 /
b100 (
b100 .
b100 +
#1545
b1 !
b1 /
b101 (
b101 .
b101 +
#1550
b11 !
b11 /
b110 (
b110 .
b110 +
#1555
b10 !
b10 /
b111 (
b111 .
b111 +
#1560
b11110 !
b11110 /
b1000 (
b1000 .
b1000 +
#1565
b10 !
b10 /
b1001 (
b1001 .
b1001 +
#1570
b1000 !
b1000 /
b1010 (
b1010 .
b1010 +
#1575
b10 !
b10 /
b1011 (
b1011 .
b1011 +
#1580
b0 !
b0 /
b1100 (
b1100 .
b1100 +
#1585
b1101 (
b1101 .
b1101 +
#1590
b1110 (
b1110 .
b1110 +
#1595
b1111 (
b1111 .
b1111 +
#1600
b101 !
b101 /
b101 0
b0 (
b0 .
b100 '
b100 -
b100 *
b0 +
#1605
1%
1$
b11101 0
b1101 !
b1101 /
b1 (
b1 .
b1 +
#1610
b11 0
0%
0$
b11 !
b11 /
b10 (
b10 .
b10 +
#1615
b10 0
b10 !
b10 /
b11 (
b11 .
b11 +
#1620
b0 0
b0 !
b0 /
b100 (
b100 .
b100 +
#1625
b101 (
b101 .
b101 +
#1630
b101 !
b101 /
b110 (
b110 .
b110 +
#1635
b101 !
b101 /
b111 (
b111 .
b111 +
#1640
b11110 !
b11110 /
b1000 (
b1000 .
b1000 +
#1645
b10 !
b10 /
b1001 (
b1001 .
b1001 +
#1650
b1000 !
b1000 /
b1010 (
b1010 .
b1010 +
#1655
b10 !
b10 /
b1011 (
b1011 .
b1011 +
#1660
b0 !
b0 /
b1100 (
b1100 .
b1100 +
#1665
b1101 (
b1101 .
b1101 +
#1670
b1110 (
b1110 .
b1110 +
#1675
b1111 (
b1111 .
b1111 +
#1680
b110 !
b110 /
b110 0
b0 (
b0 .
b101 '
b101 -
b101 *
b0 +
#1685
1%
1$
b11100 0
b1100 !
b1100 /
b1 (
b1 .
b1 +
#1690
b100 0
0%
0$
b100 !
b100 /
b10 (
b10 .
b10 +
#1695
b10 0
b10 !
b10 /
b11 (
b11 .
b11 +
#1700
b0 0
b0 !
b0 /
b100 (
b100 .
b100 +
#1705
b1 !
b1 /
b101 (
b101 .
b101 +
#1710
b101 !
b101 /
b110 (
b110 .
b110 +
#1715
b100 !
b100 /
b111 (
b111 .
b111 +
#1720
b11110 !
b11110 /
b1000 (
b1000 .
b1000 +
#1725
b10 !
b10 /
b1001 (
b1001 .
b1001 +
#1730
b1000 !
b1000 /
b1010 (
b1010 .
b1010 +
#1735
b10 !
b10 /
b1011 (
b1011 .
b1011 +
#1740
b0 !
b0 /
b1100 (
b1100 .
b1100 +
#1745
b1101 (
b1101 .
b1101 +
#1750
b1110 (
b1110 .
b1110 +
#1755
b1111 (
b1111 .
b1111 +
#1760
b111 !
b111 /
b111 0
b0 (
b0 .
b110 '
b110 -
b110 *
b0 +
#1765
1%
1$
b11011 0
b1011 !
b1011 /
b1 (
b1 .
b1 +
#1770
b101 0
0%
0$
b101 !
b101 /
b10 (
b10 .
b10 +
#1775
b10 0
b10 !
b10 /
b11 (
b11 .
b11 +
#1780
b0 0
b0 !
b0 /
b100 (
b100 .
b100 +
#1785
b101 (
b101 .
b101 +
#1790
b111 !
b111 /
b110 (
b110 .
b110 +
#1795
b111 !
b111 /
b111 (
b111 .
b111 +
#1800
b11110 !
b11110 /
b1000 (
b1000 .
b1000 +
#1805
b10 !
b10 /
b1001 (
b1001 .
b1001 +
#1810
b1000 !
b1000 /
b1010 (
b1010 .
b1010 +
#1815
b10 !
b10 /
b1011 (
b1011 .
b1011 +
#1820
b0 !
b0 /
b1100 (
b1100 .
b1100 +
#1825
b1101 (
b1101 .
b1101 +
#1830
b1110 (
b1110 .
b1110 +
#1835
b1111 (
b1111 .
b1111 +
#1840
b1000 !
b1000 /
b1000 0
b0 (
b0 .
b111 '
b111 -
b111 *
b0 +
#1845
1%
1$
b11010 0
b1010 !
b1010 /
b1 (
b1 .
b1 +
#1850
b110 0
0%
0$
b110 !
b110 /
b10 (
b10 .
b10 +
#1855
b10 0
b10 !
b10 /
b11 (
b11 .
b11 +
#1860
b0 0
b0 !
b0 /
b100 (
b100 .
b100 +
#1865
b1 !
b1 /
b101 (
b101 .
b101 +
#1870
b111 !
b111 /
b110 (
b110 .
b110 +
#1875
b110 !
b110 /
b111 (
b111 .
b111 +
#1880
b11110 !
b11110 /
b1000 (
b1000 .
b1000 +
#1885
b10 !
b10 /
b1001 (
b1001 .
b1001 +
#1890
b1000 !
b1000 /
b1010 (
b1010 .
b1010 +
#1895
b10 !
b10 /
b1011 (
b1011 .
b1011 +
#1900
b0 !
b0 /
b1100 (
b1100 .
b1100 +
#1905
b1101 (
b1101 .
b1101 +
#1910
b1110 (
b1110 .
b1110 +
#1915
b1111 (
b1111 .
b1111 +
#1920
b1001 !
b1001 /
b1001 0
b0 (
b0 .
b1000 '
b1000 -
b1000 *
b0 +
#1925
1%
1$
b11001 0
b1001 !
b1001 /
b1 (
b1 .
b1 +
#1930
b111 0
0%
0$
b111 !
b111 /
b10 (
b10 .
b10 +
#1935
b10 0
b10 !
b10 /
b11 (
b11 .
b11 +
#1940
b0 0
b0 !
b0 /
b100 (
b100 .
b100 +
#1945
b101 (
b101 .
b101 +
#1950
b1001 !
b1001 /
b110 (
b110 .
b110 +
#1955
b1001 !
b1001 /
b111 (
b111 .
b111 +
#1960
b11110 !
b11110 /
b1000 (
b1000 .
b1000 +
#1965
b10 !
b10 /
b1001 (
b1001 .
b1001 +
#1970
b1000 !
b1000 /
b1010 (
b1010 .
b1010 +
#1975
b10 !
b10 /
b1011 (
b1011 .
b1011 +
#1980
b0 !
b0 /
b1100 (
b1100 .
b1100 +
#1985
b1101 (
b1101 .
b1101 +
#1990
b1110 (
b1110 .
b1110 +
#1995
b1111 (
b1111 .
b1111 +
#2000
b1010 !
b1010 /
b1010 0
b0 (
b0 .
b1001 '
b1001 -
b1001 *
b0 +
#2005
1%
1$
b11000 0
b1000 !
b1000 /
b1 (
b1 .
b1 +
#2010
b1000 0
0%
0$
b1000 !
b1000 /
b10 (
b10 .
b10 +
#2015
b10 0
b10 !
b10 /
b11 (
b11 .
b11 +
#2020
b0 0
b0 !
b0 /
b100 (
b100 .
b100 +
#2025
b1 !
b1 /
b101 (
b101 .
b101 +
#2030
b1001 !
b1001 /
b110 (
b110 .
b110 +
#2035
b1000 !
b1000 /
b111 (
b111 .
b111 +
#2040
b11110 !
b11110 /
b1000 (
b1000 .
b1000 +
#2045
b10 !
b10 /
b1001 (
b1001 .
b1001 +
#2050
b1000 !
b1000 /
b1010 (
b1010 .
b1010 +
#2055
b10 !
b10 /
b1011 (
b1011 .
b1011 +
#2060
b0 !
b0 /
b1100 (
b1100 .
b1100 +
#2065
b1101 (
b1101 .
b1101 +
#2070
b1110 (
b1110 .
b1110 +
#2075
b1111 (
b1111 .
b1111 +
#2080
b1011 !
b1011 /
b1011 0
b0 (
b0 .
b1010 '
b1010 -
b1010 *
b0 +
#2085
1%
1$
b10111 0
b111 !
b111 /
b1 (
b1 .
b1 +
