Day25_gray_to_binary/gray_to_binary.v
module gray_to_binary #(parameter N = 8)(
    input  wire [N-1:0] gray,
    output reg  [N-1:0] binary
);

    integer i;

    always @(*) begin
        binary[N-1] = gray[N-1];

        for (i = N-2; i >= 0; i = i - 1) begin
            binary[i] = binary[i+1] ^ gray[i];
        end
    end

endmodule

Day25_gray_to_binary/tb_gray_to_binary.v
module tb_gray_to_binary;

    parameter N = 8;

    reg  [N-1:0] gray;
    wire [N-1:0] binary;

    gray_to_binary #(N) dut (
        .gray(gray),
        .binary(binary)
    );

    integer k;

    initial begin
    	    for (k = 0; k < 16; k = k + 1) begin
            gray = (k >> 1) ^ k;   // converting k (binary) into Gray for testing
            #1;
        end
        $finish;
    end
    initial begin 
	    $dumpfile("tb_gray_to_binary.vcd");
	    $dumpvars(0,tb_gray_to_binary);
    end

endmodule

Day25_gray_to_binary/tb_gray_to_binary.vcd
$date
	Tue Nov 25 07:04:14 2025
$end
$version
	Icarus Verilog
$end
$timescale
	1s
$end
$scope module tb_gray_to_binary $end
$var wire 8 ! binary [7:0] $end
$var reg 8 " gray [7:0] $end
$var integer 32 # k [31:0] $end
$scope module dut $end
$var wire 8 $ gray [7:0] $end
$var reg 8 % binary [7:0] $end
$var integer 32 & i [31:0] $end
$upscope $end
$upscope $end
$enddefinitions $end
#0
$dumpvars
b11111111111111111111111111111111 &
b0 %
b0 $
b0 #
b0 "
b0 !
$end
#1
b1 !
b1 %
b11111111111111111111111111111111 &
b1 "
b1 $
b1 #
#2
b10 !
b10 %
b11111111111111111111111111111111 &
b11 "
b11 $
b10 #
#3
b11 !
b11 %
b11111111111111111111111111111111 &
b10 "
b10 $
b11 #
#4
b100 !
b100 %
b11111111111111111111111111111111 &
b110 "
b110 $
b100 #
#5
b101 !
b101 %
b11111111111111111111111111111111 &
b111 "
b111 $
b101 #
#6
b110 !
b110 %
b11111111111111111111111111111111 &
b101 "
b101 $
b110 #
#7
b111 !
b111 %
b11111111111111111111111111111111 &
b100 "
b100 $
b111 #
#8
b1000 !
b1000 %
b11111111111111111111111111111111 &
b1100 "
b1100 $
b1000 #
#9
b1001 !
b1001 %
b11111111111111111111111111111111 &
b1101 "
b1101 $
b1001 #
#10
b1010 !
b1010 %
b11111111111111111111111111111111 &
b1111 "
b1111 $
b1010 #
#11
b1011 !
b1011 %
b11111111111111111111111111111111 &
b1110 "
b1110 $
b1011 #
#12
b1100 !
b1100 %
b11111111111111111111111111111111 &
b1010 "
b1010 $
b1100 #
#13
b1101 !
b1101 %
b11111111111111111111111111111111 &
b1011 "
b1011 $
b1101 #
#14
b1110 !
b1110 %
b11111111111111111111111111111111 &
b1001 "
b1001 $
b1110 #
#15
b1111 !
b1111 %
b11111111111111111111111111111111 &
b1000 "
b1000 $
b1111 #
#16
b10000 #
